Workbook

Sheet Orçamentos
C2: Orçamentos
H5: Markup | I5: 1.8
A6: Data | B6: Mês/Ano | C6: Cliente | D6: Produto | E6: Quantidade | F6: Impressora | G6: Filamento | H6: Custo Unitário | I6: Preço Venda Markup Unit. | J6: Total Produtos | K6: Desconto | L6: Valor Vendido | M6: Lucro % | N6: Valor Unitário
A7: 46068 | B7: =IF($A7="","",PROPER(TEXT($A7,"mmm")) & "/" & TEXT($A7,"aa")) -> Fev/26 | C7: Daniel Gomes | D7: Spectreman 20cm | E7: 1 | F7: A1-01-ECC | G7: BambuPLA SILK | H7: {=IF($A7="","",_xlfn.XLOOKUP($B7 & $D7 & $F7 & $G7, Produtos!$B:$B & Produtos!$C:$C & Produtos!$D:$D & Produtos!$E:$E, Produtos!$P:$P, ""))} -> 60.150343 | I7: =IFERROR($H7*I$5,"") -> 108.27062 | J7: =IFERROR($E7*$I7,"") -> 108.27062 | K7: 0 | M7: =IFERROR(IF(OR($L7="",$L7=0),"",($L7-$J7)/$J7),"")
A8: 46099 | B8: =IF($A8="","",PROPER(TEXT($A8,"mmm")) & "/" & TEXT($A8,"aa")) -> Mar/26 | C8: Marcelo Back (Alpha) | D8: Porta Caneta Alpha 01 Cor | E8: 1 | F8: A1-01-ECC | G8: N3D PLA High Speed | H8: {=IF($A8="","",_xlfn.XLOOKUP($B8 & $D8 & $F8 & $G8, Produtos!$B:$B & Produtos!$C:$C & Produtos!$D:$D & Produtos!$E:$E, Produtos!$P:$P, ""))} | I8: =IFERROR($H8*I$5,"") | J8: =IFERROR($E8*$I8,"") | K8: 0 | M8: =IFERROR(IF(OR($L8="",$L8=0),"",($L8-$J8)/$J8),"")
A9: 46099 | B9: =IF($A9="","",PROPER(TEXT($A9,"mmm")) & "/" & TEXT($A9,"aa")) -> Mar/26 | C9: Marcelo Back (Alpha) | D9: Cauda Moteiro 30x17mm | E9: 1 | F9: A1-01-ECC | G9: Masterprint PETG Basic | H9: {=IF($A9="","",_xlfn.XLOOKUP($B9 & $D9 & $F9 & $G9, Produtos!$B:$B & Produtos!$C:$C & Produtos!$D:$D & Produtos!$E:$E, Produtos!$P:$P, ""))} -> 14.116119 | I9: =IFERROR($H9*I$5,"") -> 25.409015 | J9: =IFERROR($E9*$I9,"") -> 25.409015 | K9: 0 | L9: 50 | M9: =IFERROR(IF(OR($L9="",$L9=0),"",($L9-$J9)/$J9),"") -> 0.96780552
A10: 46069 | B10: =IF($A10="","",PROPER(TEXT($A10,"mmm")) & "/" & TEXT($A10,"aa")) -> Fev/26 | C10: Anúncio Internet | D10: Lum. Prisma Futurista Moderna | E10: 1 | F10: A1-01-ECC | G10: Bambu Lite PLA | H10: {=IF($A10="","",_xlfn.XLOOKUP($B10 & $D10 & $F10 & $G10, Produtos!$B:$B & Produtos!$C:$C & Produtos!$D:$D & Produtos!$E:$E, Produtos!$P:$P, ""))} -> 48.092524 | I10: =IFERROR($H10*I$5,"") -> 86.566544 | J10: =IFERROR($E10*$I10,"") -> 86.566544 | M10: =IFERROR(IF(OR($L10="",$L10=0),"",($L10-$J10)/$J10),"")
A11: 46103 | B11: =IF($A11="","",PROPER(TEXT($A11,"mmm")) & "/" & TEXT($A11,"aa")) -> Mar/26 | C11: Rogério Maciel | D11: Case TRT | E11: 1 | F11: A1-01-ECC | G11: N3D PLA High Speed | H11: {=IF($A11="","",_xlfn.XLOOKUP($B11 & $D11 & $F11 & $G11, Produtos!$B:$B & Produtos!$C:$C & Produtos!$D:$D & Produtos!$E:$E, Produtos!$P:$P, ""))} -> 31.531134 | I11: =IFERROR($H11*I$5,"") -> 56.756041 | J11: =IFERROR($E11*$I11,"") -> 56.756041 | L11: 80 | M11: =IFERROR(IF(OR($L11="",$L11=0),"",($L11-$J11)/$J11),"") -> 0.40954159
A12: 46103 | B12: =IF($A12="","",PROPER(TEXT($A12,"mmm")) & "/" & TEXT($A12,"aa")) -> Mar/26 | C12: Rogério Maciel | D12: Case TRT 6 Frascos | E12: 1 | F12: A1-01-ECC | G12: N3D PLA High Speed | H12: {=IF($A12="","",_xlfn.XLOOKUP($B12 & $D12 & $F12 & $G12, Produtos!$B:$B & Produtos!$C:$C & Produtos!$D:$D & Produtos!$E:$E, Produtos!$P:$P, ""))} -> 30.784477 | I12: =IFERROR($H12*I$5,"") -> 55.412059 | J12: =IFERROR($E12*$I12,"") -> 55.412059 | L12: 95 | M12: =IFERROR(IF(OR($L12="",$L12=0),"",($L12-$J12)/$J12),"") -> 0.71442827
A13: 46103 | B13: =IF($A13="","",PROPER(TEXT($A13,"mmm")) & "/" & TEXT($A13,"aa")) -> Mar/26 | C13: Marcelo Back (Alpha) | D13: Porta Caneta Minecraft Dinamite | E13: 1 | F13: A1-01-ECC | G13: Bambu Lite PLA | H13: {=IF($A13="","",_xlfn.XLOOKUP($B13 & $D13 & $F13 & $G13, Produtos!$B:$B & Produtos!$C:$C & Produtos!$D:$D & Produtos!$E:$E, Produtos!$P:$P, ""))} -> 39.47672 | I13: =IFERROR($H13*I$5,"") -> 71.058096 | J13: =IFERROR($E13*$I13,"") -> 71.058096 | L13: 85 | M13: =IFERROR(IF(OR($L13="",$L13=0),"",($L13-$J13)/$J13),"") -> 0.1962043
A14: 46072 | B14: =IF($A14="","",PROPER(TEXT($A14,"mmm")) & "/" & TEXT($A14,"aa")) -> Fev/26 | C14: Marcelo Back (Alpha) | D14: Porta Caneta Alpha 02 Cores | E14: 1 | F14: A1-01-ECC | G14: N3D PLA High Speed | H14: {=IF($A14="","",_xlfn.XLOOKUP($B14 & $D14 & $F14 & $G14, Produtos!$B:$B & Produtos!$C:$C & Produtos!$D:$D & Produtos!$E:$E, Produtos!$P:$P, ""))} -> 32.761642 | I14: =IFERROR($H14*I$5,"") -> 58.970956 | J14: =IFERROR($E14*$I14,"") -> 58.970956 | L14: 65 | M14: =IFERROR(IF(OR($L14="",$L14=0),"",($L14-$J14)/$J14),"") -> 0.10223751
A15: 46105 | B15: =IF($A15="","",PROPER(TEXT($A15,"mmm")) & "/" & TEXT($A15,"aa")) -> Mar/26 | C15: Andrei Fabrício | D15: Enfeite Família | E15: 1 | F15: A1-01-ECC | G15: Bambu Lite PLA | H15: {=IF($A15="","",_xlfn.XLOOKUP($B15 & $D15 & $F15 & $G15, Produtos!$B:$B & Produtos!$C:$C & Produtos!$D:$D & Produtos!$E:$E, Produtos!$P:$P, ""))} -> 14.559259 | I15: =IFERROR($H15*I$5,"") -> 26.206665 | J15: =IFERROR($E15*$I15,"") -> 26.206665 | L15: 50 | M15: =IFERROR(IF(OR($L15="",$L15=0),"",($L15-$J15)/$J15),"") -> 0.90791157
A16: 46119 | B16: =IF($A16="","",PROPER(TEXT($A16,"mmm")) & "/" & TEXT($A16,"aa")) -> Abr/26 | C16: Clodoaldo | D16: Caixa Munição 9mm | E16: 1 | F16: A1-01-ECC | G16: Voolt3D PLA | H16: {=IF($A16="","",_xlfn.XLOOKUP($B16 & $D16 & $F16 & $G16, Produtos!$B:$B & Produtos!$C:$C & Produtos!$D:$D & Produtos!$E:$E, Produtos!$P:$P, ""))} -> 30.175959 | I16: =IFERROR($H16*I$5,"") -> 54.316726 | J16: =IFERROR($E16*$I16,"") -> 54.316726 | L16: 65 | M16: =IFERROR(IF(OR($L16="",$L16=0),"",($L16-$J16)/$J16),"") -> 0.19668479
A17: 46119 | B17: =IF($A17="","",PROPER(TEXT($A17,"mmm")) & "/" & TEXT($A17,"aa")) -> Abr/26 | C17: Clodoaldo | D17: Estojo de Clipe 223 556 300 10_15rd e Carregador Rápido | E17: 1 | F17: A1-01-ECC | G17: Voolt3D PLA | H17: {=IF($A17="","",_xlfn.XLOOKUP($B17 & $D17 & $F17 & $G17, Produtos!$B:$B & Produtos!$C:$C & Produtos!$D:$D & Produtos!$E:$E, Produtos!$P:$P, ""))} -> 66.618161 | I17: =IFERROR($H17*I$5,"") -> 119.91269 | J17: =IFERROR($E17*$I17,"") -> 119.91269 | M17: =IFERROR(IF(OR($L17="",$L17=0),"",($L17-$J17)/$J17),"")
A18: 46124 | B18: =IF($A18="","",PROPER(TEXT($A18,"mmm")) & "/" & TEXT($A18,"aa")) -> Abr/26 | C18: Juliana | D18: BTS Prateleira de Exibição Temática | E18: 1 | F18: A1-01-ECC | G18: Bambu Lite PLA | H18: {=IF($A18="","",_xlfn.XLOOKUP($B18 & $D18 & $F18 & $G18, Produtos!$B:$B & Produtos!$C:$C & Produtos!$D:$D & Produtos!$E:$E, Produtos!$P:$P, ""))} -> 28.502471 | I18: =IFERROR($H18*I$5,"") -> 51.304448 | J18: =IFERROR($E18*$I18,"") -> 51.304448 | L18: 80 | M18: =IFERROR(IF(OR($L18="",$L18=0),"",($L18-$J18)/$J18),"") -> 0.559319
A19: 46125 | B19: =IF($A19="","",PROPER(TEXT($A19,"mmm")) & "/" & TEXT($A19,"aa")) -> Abr/26 | C19: Verinha | D19: Vaso Felicia Espiral 12cm | E19: 1 | F19: A1-01-ECC | G19: Masterprint PETG Basic | H19: {=IF($A19="","",_xlfn.XLOOKUP($B19 & $D19 & $F19 & $G19, Produtos!$B:$B & Produtos!$C:$C & Produtos!$D:$D & Produtos!$E:$E, Produtos!$P:$P, ""))} -> 6.9845288 | I19: =IFERROR($H19*I$5,"") -> 12.572152 | J19: =IFERROR($E19*$I19,"") -> 12.572152 | M19: =IFERROR(IF(OR($L19="",$L19=0),"",($L19-$J19)/$J19),"")
A20: 46126 | B20: =IF($A20="","",PROPER(TEXT($A20,"mmm")) & "/" & TEXT($A20,"aa")) -> Abr/26 | C20: Verinha | D20: Chaveiro Vinil BTS com Nome | E20: 1 | F20: A1-01-ECC | G20: Bambu Lite PLA | H20: {=IF($A20="","",_xlfn.XLOOKUP($B20 & $D20 & $F20 & $G20, Produtos!$B:$B & Produtos!$C:$C & Produtos!$D:$D & Produtos!$E:$E, Produtos!$P:$P, ""))} -> 8.1070666 | I20: =IFERROR($H20*I$5,"") -> 14.59272 | J20: =IFERROR($E20*$I20,"") -> 14.59272 | M20: =IFERROR(IF(OR($L20="",$L20=0),"",($L20-$J20)/$J20),"")
A21: 46126 | B21: =IF($A21="","",PROPER(TEXT($A21,"mmm")) & "/" & TEXT($A21,"aa")) -> Abr/26 | C21: Verinha | D21: Chaveiro Vinil BTS com Nome Mesa | E21: 1 | F21: A1-01-ECC | G21: Bambu Lite PLA | H21: {=IF($A21="","",_xlfn.XLOOKUP($B21 & $D21 & $F21 & $G21, Produtos!$B:$B & Produtos!$C:$C & Produtos!$D:$D & Produtos!$E:$E, Produtos!$P:$P, ""))} -> 31.250826 | I21: =IFERROR($H21*I$5,"") -> 56.251487 | J21: =IFERROR($E21*$I21,"") -> 56.251487 | M21: =IFERROR(IF(OR($L21="",$L21=0),"",($L21-$J21)/$J21),"")
A22: 46126 | B22: =IF($A22="","",PROPER(TEXT($A22,"mmm")) & "/" & TEXT($A22,"aa")) -> Abr/26 | C22: Juliana | D22: Estante de Brincadeiras | E22: 1 | F22: A1-01-ECC | G22: Masterprint PETG Basic | H22: {=IF($A22="","",_xlfn.XLOOKUP($B22 & $D22 & $F22 & $G22, Produtos!$B:$B & Produtos!$C:$C & Produtos!$D:$D & Produtos!$E:$E, Produtos!$P:$P, ""))} -> 73.062884 | I22: =IFERROR($H22*I$5,"") -> 131.51319 | J22: =IFERROR($E22*$I22,"") -> 131.51319 | M22: =IFERROR(IF(OR($L22="",$L22=0),"",($L22-$J22)/$J22),"")
A23: 46127 | B23: =IF($A23="","",PROPER(TEXT($A23,"mmm")) & "/" & TEXT($A23,"aa")) -> Abr/26 | C23: Karina | D23: Luminária Bulldog | E23: 1 | F23: A1-01-ECC | G23: N3D PLA High Speed | H23: {=IF($A23="","",_xlfn.XLOOKUP($B23 & $D23 & $F23 & $G23, Produtos!$B:$B & Produtos!$C:$C & Produtos!$D:$D & Produtos!$E:$E, Produtos!$P:$P, ""))} -> 69.01897 | I23: =IFERROR($H23*I$5,"") -> 124.23415 | J23: =IFERROR($E23*$I23,"") -> 124.23415 | L23: 195 | M23: =IFERROR(IF(OR($L23="",$L23=0),"",($L23-$J23)/$J23),"") -> 0.56961678
A24: 46127 | B24: =IF($A24="","",PROPER(TEXT($A24,"mmm")) & "/" & TEXT($A24,"aa")) -> Abr/26 | C24: Juliana | D24: BTS Fliptext Chaveiro - 10 Un | E24: 1 | F24: A1-01-ECC | G24: N3D PLA High Speed | H24: {=IF($A24="","",_xlfn.XLOOKUP($B24 & $D24 & $F24 & $G24, Produtos!$B:$B & Produtos!$C:$C & Produtos!$D:$D & Produtos!$E:$E, Produtos!$P:$P, ""))} -> 38.723933 | I24: =IFERROR($H24*I$5,"") -> 69.70308 | J24: =IFERROR($E24*$I24,"") -> 69.70308 | M24: =IFERROR(IF(OR($L24="",$L24=0),"",($L24-$J24)/$J24),"") | N24: 15,00 cada
A25: 46127 | B25: =IF($A25="","",PROPER(TEXT($A25,"mmm")) & "/" & TEXT($A25,"aa")) -> Abr/26 | C25: Juliana | D25: BTS ARMY Fliptext - 4 un | E25: 1 | F25: A1-01-ECC | G25: N3D PLA High Speed | H25: {=IF($A25="","",_xlfn.XLOOKUP($B25 & $D25 & $F25 & $G25, Produtos!$B:$B & Produtos!$C:$C & Produtos!$D:$D & Produtos!$E:$E, Produtos!$P:$P, ""))} -> 34.429701 | I25: =IFERROR($H25*I$5,"") -> 61.973463 | J25: =IFERROR($E25*$I25,"") -> 61.973463 | L25: 80 | M25: =IFERROR(IF(OR($L25="",$L25=0),"",($L25-$J25)/$J25),"") -> 0.2908751 | N25: 80,00 cada
A26: 46128 | B26: =IF($A26="","",PROPER(TEXT($A26,"mmm")) & "/" & TEXT($A26,"aa")) -> Abr/26 | C26: Marcelo Back (Alpha) | D26: Ovo Dragrão | E26: 1 | F26: A1-01-ECC | G26: N3D PLA High Speed | H26: {=IF($A26="","",_xlfn.XLOOKUP($B26 & $D26 & $F26 & $G26, Produtos!$B:$B & Produtos!$C:$C & Produtos!$D:$D & Produtos!$E:$E, Produtos!$P:$P, ""))} -> 11.698906 | I26: =IFERROR($H26*I$5,"") -> 21.05803 | J26: =IFERROR($E26*$I26,"") -> 21.05803 | L26: 65 | M26: =IFERROR(IF(OR($L26="",$L26=0),"",($L26-$J26)/$J26),"") -> 2.0867085
A27: 46129 | B27: =IF($A27="","",PROPER(TEXT($A27,"mmm")) & "/" & TEXT($A27,"aa")) -> Abr/26 | C27: Karina Castilhos | D27: Luminária Bulldog | E27: 1 | F27: A1-01-ECC | G27: N3D PLA High Speed | H27: {=IF($A27="","",_xlfn.XLOOKUP($B27 & $D27 & $F27 & $G27, Produtos!$B:$B & Produtos!$C:$C & Produtos!$D:$D & Produtos!$E:$E, Produtos!$P:$P, ""))} -> 69.01897 | I27: =IFERROR($H27*I$5,"") -> 124.23415 | J27: =IFERROR($E27*$I27,"") -> 124.23415 | L27: 195 | M27: =IFERROR(IF(OR($L27="",$L27=0),"",($L27-$J27)/$J27),"") -> 0.56961678
A28: 46129 | B28: =IF($A28="","",PROPER(TEXT($A28,"mmm")) & "/" & TEXT($A28,"aa")) -> Abr/26 | C28: Raquel Conccato | D28: BTS ARMY Fliptext - 4 un | E28: 1 | F28: A1-01-ECC | G28: N3D PLA High Speed | H28: {=IF($A28="","",_xlfn.XLOOKUP($B28 & $D28 & $F28 & $G28, Produtos!$B:$B & Produtos!$C:$C & Produtos!$D:$D & Produtos!$E:$E, Produtos!$P:$P, ""))} -> 34.429701 | I28: =IFERROR($H28*I$5,"") -> 61.973463 | J28: =IFERROR($E28*$I28,"") -> 61.973463 | L28: 80 | M28: =IFERROR(IF(OR($L28="",$L28=0),"",($L28-$J28)/$J28),"") -> 0.2908751 | N28: 80,00 cada
A29: 46130 | B29: =IF($A29="","",PROPER(TEXT($A29,"mmm")) & "/" & TEXT($A29,"aa")) -> Abr/26 | C29: Eder | D29: Suporte Celular Banco Carro | E29: 1 | F29: A1-01-ECC | G29: N3D PLA High Speed | H29: {=IF($A29="","",_xlfn.XLOOKUP($B29 & $D29 & $F29 & $G29, Produtos!$B:$B & Produtos!$C:$C & Produtos!$D:$D & Produtos!$E:$E, Produtos!$P:$P, ""))} -> 6.5603369 | I29: =IFERROR($H29*I$5,"") -> 11.808606 | J29: =IFERROR($E29*$I29,"") -> 11.808606 | L29: 20 | M29: =IFERROR(IF(OR($L29="",$L29=0),"",($L29-$J29)/$J29),"") -> 0.69367996
A30: 46130 | B30: =IF($A30="","",PROPER(TEXT($A30,"mmm")) & "/" & TEXT($A30,"aa")) -> Abr/26 | C30: Eder | D30: Suporte Celular Banco Carro 6 Un | E30: 1 | F30: A1-01-ECC | G30: N3D PLA High Speed | H30: {=IF($A30="","",_xlfn.XLOOKUP($B30 & $D30 & $F30 & $G30, Produtos!$B:$B & Produtos!$C:$C & Produtos!$D:$D & Produtos!$E:$E, Produtos!$P:$P, ""))} | I30: =IFERROR($H30*I$5,"") | J30: =IFERROR($E30*$I30,"") | L30: 115 | M30: =IFERROR(IF(OR($L30="",$L30=0),"",($L30-$J30)/$J30),"") | N30: 19,00 cada
A31: 46133 | B31: =IF($A31="","",PROPER(TEXT($A31,"mmm")) & "/" & TEXT($A31,"aa")) -> Abr/26 | C31: Leonardo Pinto | D31: Suporte Aro Headphone + Controle | E31: 1 | F31: A1-01-ECC | G31: N3D PLA High Speed | H31: {=IF($A31="","",_xlfn.XLOOKUP($B31 & $D31 & $F31 & $G31, Produtos!$B:$B & Produtos!$C:$C & Produtos!$D:$D & Produtos!$E:$E, Produtos!$P:$P, ""))} -> 59.850075 | I31: =IFERROR($H31*I$5,"") -> 107.73013 | J31: =IFERROR($E31*$I31,"") -> 107.73013 | L31: 200 | M31: =IFERROR(IF(OR($L31="",$L31=0),"",($L31-$J31)/$J31),"") -> 0.85649076
A32: 46133 | B32: =IF($A32="","",PROPER(TEXT($A32,"mmm")) & "/" & TEXT($A32,"aa")) -> Abr/26 | C32: Marcelo Back (Alpha) | D32: Expositor com Display | E32: 1 | F32: A1-01-ECC | G32: N3D PLA High Speed | H32: {=IF($A32="","",_xlfn.XLOOKUP($B32 & $D32 & $F32 & $G32, Produtos!$B:$B & Produtos!$C:$C & Produtos!$D:$D & Produtos!$E:$E, Produtos!$P:$P, ""))} -> 15.75669 | I32: =IFERROR($H32*I$5,"") -> 28.362042 | J32: =IFERROR($E32*$I32,"") -> 28.362042 | L32: 35 | M32: =IFERROR(IF(OR($L32="",$L32=0),"",($L32-$J32)/$J32),"") -> 0.23404374
A33: 46133 | B33: =IF($A33="","",PROPER(TEXT($A33,"mmm")) & "/" & TEXT($A33,"aa")) -> Abr/26 | C33: Marcelo Back (Alpha) | D33: Chav. Capsula 12 - 5 Un | E33: 1 | F33: A1-01-ECC | G33: N3D PLA High Speed | H33: {=IF($A33="","",_xlfn.XLOOKUP($B33 & $D33 & $F33 & $G33, Produtos!$B:$B & Produtos!$C:$C & Produtos!$D:$D & Produtos!$E:$E, Produtos!$P:$P, ""))} -> 14.177787 | I33: =IFERROR($H33*I$5,"") -> 25.520017 | J33: =IFERROR($E33*$I33,"") -> 25.520017 | L33: 32.5 | M33: =IFERROR(IF(OR($L33="",$L33=0),"",($L33-$J33)/$J33),"") -> 0.27351014 | N33: 6,50 cada
A34: 46133 | B34: =IF($A34="","",PROPER(TEXT($A34,"mmm")) & "/" & TEXT($A34,"aa")) -> Abr/26 | C34: Marcelo Back (Alpha) | D34: Chav. Granada - 5 Un | E34: 1 | F34: A1-01-ECC | G34: N3D PLA High Speed | H34: {=IF($A34="","",_xlfn.XLOOKUP($B34 & $D34 & $F34 & $G34, Produtos!$B:$B & Produtos!$C:$C & Produtos!$D:$D & Produtos!$E:$E, Produtos!$P:$P, ""))} -> 17.731685 | I34: =IFERROR($H34*I$5,"") -> 31.917032 | J34: =IFERROR($E34*$I34,"") -> 31.917032 | L34: 37.5 | M34: =IFERROR(IF(OR($L34="",$L34=0),"",($L34-$J34)/$J34),"") -> 0.17492127 | N34: 7,50 cada
A35: 46133 | B35: =IF($A35="","",PROPER(TEXT($A35,"mmm")) & "/" & TEXT($A35,"aa")) -> Abr/26 | C35: Clodoaldo | D35: Suporte AR com Carregador | E35: 1 | F35: A1-01-ECC | G35: N3D PLA High Speed | H35: {=IF($A35="","",_xlfn.XLOOKUP($B35 & $D35 & $F35 & $G35, Produtos!$B:$B & Produtos!$C:$C & Produtos!$D:$D & Produtos!$E:$E, Produtos!$P:$P, ""))} -> 13.287323 | I35: =IFERROR($H35*I$5,"") -> 23.917182 | J35: =IFERROR($E35*$I35,"") -> 23.917182 | L35: 50 | M35: =IFERROR(IF(OR($L35="",$L35=0),"",($L35-$J35)/$J35),"") -> 1.0905473
A36: 46133 | B36: =IF($A36="","",PROPER(TEXT($A36,"mmm")) & "/" & TEXT($A36,"aa")) -> Abr/26 | C36: Clodoaldo | D36: Bloco de Torno 9mm | E36: 1 | F36: A1-01-ECC | G36: N3D PLA High Speed | H36: {=IF($A36="","",_xlfn.XLOOKUP($B36 & $D36 & $F36 & $G36, Produtos!$B:$B & Produtos!$C:$C & Produtos!$D:$D & Produtos!$E:$E, Produtos!$P:$P, ""))} -> 11.607055 | I36: =IFERROR($H36*I$5,"") -> 20.8927 | J36: =IFERROR($E36*$I36,"") -> 20.8927 | L36: 35 | M36: =IFERROR(IF(OR($L36="",$L36=0),"",($L36-$J36)/$J36),"") -> 0.67522629
A37: 46133 | B37: =IF($A37="","",PROPER(TEXT($A37,"mmm")) & "/" & TEXT($A37,"aa")) -> Abr/26 | C37: Clodoaldo | D37: Bloco de Torno Fuzil | E37: 1 | F37: A1-01-ECC | G37: N3D PLA High Speed | H37: {=IF($A37="","",_xlfn.XLOOKUP($B37 & $D37 & $F37 & $G37, Produtos!$B:$B & Produtos!$C:$C & Produtos!$D:$D & Produtos!$E:$E, Produtos!$P:$P, ""))} -> 10.687965 | I37: =IFERROR($H37*I$5,"") -> 19.238338 | J37: =IFERROR($E37*$I37,"") -> 19.238338 | L37: 40 | M37: =IFERROR(IF(OR($L37="",$L37=0),"",($L37-$J37)/$J37),"") -> 1.0791817
A38: 46133 | B38: =IF($A38="","",PROPER(TEXT($A38,"mmm")) & "/" & TEXT($A38,"aa")) -> Abr/26 | C38: Clodoaldo | D38: Bumper GX4 | E38: 1 | F38: A1-01-ECC | G38: N3D PLA High Speed | H38: {=IF($A38="","",_xlfn.XLOOKUP($B38 & $D38 & $F38 & $G38, Produtos!$B:$B & Produtos!$C:$C & Produtos!$D:$D & Produtos!$E:$E, Produtos!$P:$P, ""))} -> 1.4618406 | I38: =IFERROR($H38*I$5,"") -> 2.6313131 | J38: =IFERROR($E38*$I38,"") -> 2.6313131 | L38: 10 | M38: =IFERROR(IF(OR($L38="",$L38=0),"",($L38-$J38)/$J38),"") -> 2.8003839
A39: 46133 | B39: =IF($A39="","",PROPER(TEXT($A39,"mmm")) & "/" & TEXT($A39,"aa")) -> Abr/26 | C39: Clodoaldo | D39: Bumper G3 | E39: 1 | F39: A1-01-ECC | G39: N3D PLA High Speed | H39: {=IF($A39="","",_xlfn.XLOOKUP($B39 & $D39 & $F39 & $G39, Produtos!$B:$B & Produtos!$C:$C & Produtos!$D:$D & Produtos!$E:$E, Produtos!$P:$P, ""))} -> 1.252137 | I39: =IFERROR($H39*I$5,"") -> 2.2538466 | J39: =IFERROR($E39*$I39,"") -> 2.2538466 | L39: 10 | M39: =IFERROR(IF(OR($L39="",$L39=0),"",($L39-$J39)/$J39),"") -> 3.4368591
A40: 46133 | B40: =IF($A40="","",PROPER(TEXT($A40,"mmm")) & "/" & TEXT($A40,"aa")) -> Abr/26 | C40: Clodoaldo | D40: Empunhadura AR-15 MLOK | E40: 1 | F40: A1-01-ECC | G40: N3D PLA High Speed | H40: {=IF($A40="","",_xlfn.XLOOKUP($B40 & $D40 & $F40 & $G40, Produtos!$B:$B & Produtos!$C:$C & Produtos!$D:$D & Produtos!$E:$E, Produtos!$P:$P, ""))} -> 3.1308264 | I40: =IFERROR($H40*I$5,"") -> 5.6354875 | J40: =IFERROR($E40*$I40,"") -> 5.6354875 | L40: 35 | M40: =IFERROR(IF(OR($L40="",$L40=0),"",($L40-$J40)/$J40),"") -> 5.2106428
A41: 46134 | B41: =IF($A41="","",PROPER(TEXT($A41,"mmm")) & "/" & TEXT($A41,"aa")) -> Abr/26 | C41: Amigo Tom | D41: Suporte Celular Mesa | E41: 1 | F41: A1-01-ECC | G41: N3D PLA High Speed | H41: {=IF($A41="","",_xlfn.XLOOKUP($B41 & $D41 & $F41 & $G41, Produtos!$B:$B & Produtos!$C:$C & Produtos!$D:$D & Produtos!$E:$E, Produtos!$P:$P, ""))} -> 2.9872264 | I41: =IFERROR($H41*I$5,"") -> 5.3770075 | J41: =IFERROR($E41*$I41,"") -> 5.3770075 | L41: 15 | M41: =IFERROR(IF(OR($L41="",$L41=0),"",($L41-$J41)/$J41),"") -> 1.7896558
A42: 46135 | B42: =IF($A42="","",PROPER(TEXT($A42,"mmm")) & "/" & TEXT($A42,"aa")) -> Abr/26 | C42: Luciano Ascenso | D42: Caixa de Jóias Coração | E42: 1 | F42: A1-01-ECC | G42: N3D PLA High Speed | H42: {=IF($A42="","",_xlfn.XLOOKUP($B42 & $D42 & $F42 & $G42, Produtos!$B:$B & Produtos!$C:$C & Produtos!$D:$D & Produtos!$E:$E, Produtos!$P:$P, ""))} -> 122.20249 | I42: =IFERROR($H42*I$5,"") -> 219.96449 | J42: =IFERROR($E42*$I42,"") -> 219.96449 | L42: 250 | M42: =IFERROR(IF(OR($L42="",$L42=0),"",($L42-$J42)/$J42),"") -> 0.13654709
A43: 46135 | B43: =IF($A43="","",PROPER(TEXT($A43,"mmm")) & "/" & TEXT($A43,"aa")) -> Abr/26 | C43: Luciano Ascenso | D43: Kit Pote Coração | E43: 1 | F43: A1-01-ECC | G43: N3D PLA High Speed | H43: {=IF($A43="","",_xlfn.XLOOKUP($B43 & $D43 & $F43 & $G43, Produtos!$B:$B & Produtos!$C:$C & Produtos!$D:$D & Produtos!$E:$E, Produtos!$P:$P, ""))} -> 19.765363 | I43: =IFERROR($H43*I$5,"") -> 35.577653 | J43: =IFERROR($E43*$I43,"") -> 35.577653 | L43: 95 | M43: =IFERROR(IF(OR($L43="",$L43=0),"",($L43-$J43)/$J43),"") -> 1.6702155
B44: =IF($A44="","",PROPER(TEXT($A44,"mmm")) & "/" & TEXT($A44,"aa")) | H44: {=IF($A44="","",_xlfn.XLOOKUP($B44 & $D44 & $F44 & $G44, Produtos!$B:$B & Produtos!$C:$C & Produtos!$D:$D & Produtos!$E:$E, Produtos!$P:$P, ""))} | I44: =IFERROR($H44*I$5,"") | J44: =IFERROR($E44*$I44,"") | M44: =IFERROR(IF(OR($L44="",$L44=0),"",($L44-$J44)/$J44),"")
B45: =IF($A45="","",PROPER(TEXT($A45,"mmm")) & "/" & TEXT($A45,"aa")) | H45: {=IF($A45="","",_xlfn.XLOOKUP($B45 & $D45 & $F45 & $G45, Produtos!$B:$B & Produtos!$C:$C & Produtos!$D:$D & Produtos!$E:$E, Produtos!$P:$P, ""))} | I45: =IFERROR($H45*I$5,"") | J45: =IFERROR($E45*$I45,"") | M45: =IFERROR(IF(OR($L45="",$L45=0),"",($L45-$J45)/$J45),"")
B46: =IF($A46="","",PROPER(TEXT($A46,"mmm")) & "/" & TEXT($A46,"aa")) | H46: {=IF($A46="","",_xlfn.XLOOKUP($B46 & $D46 & $F46 & $G46, Produtos!$B:$B & Produtos!$C:$C & Produtos!$D:$D & Produtos!$E:$E, Produtos!$P:$P, ""))} | I46: =IFERROR($H46*I$5,"") | J46: =IFERROR($E46*$I46,"") | M46: =IFERROR(IF(OR($L46="",$L46=0),"",($L46-$J46)/$J46),"")
B47: =IF($A47="","",PROPER(TEXT($A47,"mmm")) & "/" & TEXT($A47,"aa")) | H47: {=IF($A47="","",_xlfn.XLOOKUP($B47 & $D47 & $F47 & $G47, Produtos!$B:$B & Produtos!$C:$C & Produtos!$D:$D & Produtos!$E:$E, Produtos!$P:$P, ""))} | I47: =IFERROR($H47*I$5,"") | J47: =IFERROR($E47*$I47,"") | M47: =IFERROR(IF(OR($L47="",$L47=0),"",($L47-$J47)/$J47),"")
B48: =IF($A48="","",PROPER(TEXT($A48,"mmm")) & "/" & TEXT($A48,"aa")) | H48: {=IF($A48="","",_xlfn.XLOOKUP($B48 & $D48 & $F48 & $G48, Produtos!$B:$B & Produtos!$C:$C & Produtos!$D:$D & Produtos!$E:$E, Produtos!$P:$P, ""))} | I48: =IFERROR($H48*I$5,"") | J48: =IFERROR($E48*$I48,"") | M48: =IFERROR(IF(OR($L48="",$L48=0),"",($L48-$J48)/$J48),"")

Sheet Vendas
C2: Controle de Vendas
H5: Markup | I5: 1.8
A6: Data | B6: Mês/Ano | C6: Cliente | D6: Produto | E6: Quantidade | F6: Impressora | G6: Filamento | H6: Custo Unitário | I6: Preço Venda Markup Unit. | J6: Total Produtos | K6: Desconto | L6: Valor Vendido | M6: Lucro %
A7: 46057 | B7: =IF($A7="","",PROPER(TEXT($A7,"mmm")) & "/" & TEXT($A7,"aa")) -> Fev/26 | C7: Lusciano Ascenso | D7: Miniatura Leonardo | E7: 1 | F7: A1-01-ECC | G7: N3D PLA High Speed | H7: {=_xlfn.XLOOKUP($B7 & $D7 & $F7 & $G7, Produtos!$B:$B & Produtos!$C:$C & Produtos!$D:$D & Produtos!$E:$E, Produtos!$P:$P, "")} -> 47.063358 | I7: =IFERROR($H7*I$5,"") -> 84.714045 | J7: =IFERROR($E7*$I7,"") -> 84.714045 | K7: 0 | L7: 150 | M7: =IFERROR(IF(OR($L7="",$L7=0),"",($L7-$J7)/$J7),"") -> 0.77066271
A8: 46065 | B8: =IF($A8="","",PROPER(TEXT($A8,"mmm")) & "/" & TEXT($A8,"aa")) -> Fev/26 | C8: Fabiano Dilda | D8: Miniatura CAC Fabiano | E8: 1 | F8: A1-01-ECC | G8: N3D PLA High Speed | H8: {=_xlfn.XLOOKUP($B8 & $D8 & $F8 & $G8, Produtos!$B:$B & Produtos!$C:$C & Produtos!$D:$D & Produtos!$E:$E, Produtos!$P:$P, "")} -> 33.697545 | I8: =IFERROR($H8*I$5,"") -> 60.655581 | J8: =IFERROR($E8*$I8,"") -> 60.655581 | K8: 40 | L8: 230 | M8: =IFERROR(IF(OR($L8="",$L8=0),"",($L8-$J8)/$J8),"") -> 2.7919017 | N8: 190
A9: 46065 | B9: =IF($A9="","",PROPER(TEXT($A9,"mmm")) & "/" & TEXT($A9,"aa")) -> Fev/26 | C9: Cristiane Mengue | D9: Foguete NASA Educ. | E9: 1 | F9: A1-01-ECC | G9: N3D PLA High Speed | H9: {=_xlfn.XLOOKUP($B9 & $D9 & $F9 & $G9, Produtos!$B:$B & Produtos!$C:$C & Produtos!$D:$D & Produtos!$E:$E, Produtos!$P:$P, "")} -> 18.631928 | I9: =IFERROR($H9*I$5,"") -> 33.53747 | J9: =IFERROR($E9*$I9,"") -> 33.53747 | K9: 0 | L9: 50 | M9: =IFERROR(IF(OR($L9="",$L9=0),"",($L9-$J9)/$J9),"") -> 0.49086978
A10: 46071 | B10: =IF($A10="","",PROPER(TEXT($A10,"mmm")) & "/" & TEXT($A10,"aa")) -> Fev/26 | C10: Fabiano Dilda | D10: Vaso Espiral com Pés Peq. | E10: 1 | F10: A1-01-ECC | G10: N3D PLA High Speed | H10: {=_xlfn.XLOOKUP($B10 & $D10 & $F10 & $G10, Produtos!$B:$B & Produtos!$C:$C & Produtos!$D:$D & Produtos!$E:$E, Produtos!$P:$P, "")} -> 12.990132 | I10: =IFERROR($H10*I$5,"") -> 23.382237 | J10: =IFERROR($E10*$I10,"") -> 23.382237 | K10: 0 | L10: 50 | M10: =IFERROR(IF(OR($L10="",$L10=0),"",($L10-$J10)/$J10),"") -> 1.1383753
A11: 46072 | B11: =IF($A11="","",PROPER(TEXT($A11,"mmm")) & "/" & TEXT($A11,"aa")) -> Fev/26 | C11: Claro Soares (Alpha) | D11: Miniatura CAC Soares | E11: 1 | F11: A1-01-ECC | G11: N3D PLA High Speed | H11: {=_xlfn.XLOOKUP($B11 & $D11 & $F11 & $G11, Produtos!$B:$B & Produtos!$C:$C & Produtos!$D:$D & Produtos!$E:$E, Produtos!$P:$P, "")} -> 47.23397 | I11: =IFERROR($H11*I$5,"") -> 85.021145 | J11: =IFERROR($E11*$I11,"") -> 85.021145 | K11: 0 | L11: 230 | M11: =IFERROR(IF(OR($L11="",$L11=0),"",($L11-$J11)/$J11),"") -> 1.7052094
A12: 46074 | B12: =IF($A12="","",PROPER(TEXT($A12,"mmm")) & "/" & TEXT($A12,"aa")) -> Fev/26 | C12: Felipe Pacheco | D12: Escultura N. Sra. Div. Prev. | E12: 1 | F12: A1-01-ECC | G12: Masterprint PETG Basic | H12: {=_xlfn.XLOOKUP($B12 & $D12 & $F12 & $G12, Produtos!$B:$B & Produtos!$C:$C & Produtos!$D:$D & Produtos!$E:$E, Produtos!$P:$P, "")} -> 21.873128 | I12: =IFERROR($H12*I$5,"") -> 39.37163 | J12: =IFERROR($E12*$I12,"") -> 39.37163 | K12: 0 | L12: 50 | M12: =IFERROR(IF(OR($L12="",$L12=0),"",($L12-$J12)/$J12),"") -> 0.26994997
A13: 46074 | B13: =IF($A13="","",PROPER(TEXT($A13,"mmm")) & "/" & TEXT($A13,"aa")) -> Fev/26 | C13: Felipe Pacheco | D13: Vaso Mindfulness e Porta Vela | E13: 1 | F13: A1-01-ECC | G13: Masterprint PETG Basic | H13: {=_xlfn.XLOOKUP($B13 & $D13 & $F13 & $G13, Produtos!$B:$B & Produtos!$C:$C & Produtos!$D:$D & Produtos!$E:$E, Produtos!$P:$P, "")} -> 61.960953 | I13: =IFERROR($H13*I$5,"") -> 111.52971 | J13: =IFERROR($E13*$I13,"") -> 111.52971 | K13: 40 | L13: 150 | M13: =IFERROR(IF(OR($L13="",$L13=0),"",($L13-$J13)/$J13),"") -> 0.34493306
A14: 46055 | B14: =IF($A14="","",PROPER(TEXT($A14,"mmm")) & "/" & TEXT($A14,"aa")) -> Fev/26 | C14: Marcelo Bach (Alpha) | D14: Chav. Glock 17 5cm | E14: 16 | F14: A1-01-ECC | G14: N3D PLA High Speed | H14: {=_xlfn.XLOOKUP($B14 & $D14 & $F14 & $G14, Produtos!$B:$B & Produtos!$C:$C & Produtos!$D:$D & Produtos!$E:$E, Produtos!$P:$P, "")} -> 1.1891693 | I14: =IFERROR($H14*I$5,"") -> 2.1405047 | J14: =IFERROR($E14*$I14,"") -> 34.248075 | L14: 104 | M14: =IFERROR(IF(OR($L14="",$L14=0),"",($L14-$J14)/$J14),"") -> 2.036667
A15: 46067 | B15: =IF($A15="","",PROPER(TEXT($A15,"mmm")) & "/" & TEXT($A15,"aa")) -> Fev/26 | C15: Fabio Olgins | D15: Chav. Glock 17 5cm | E15: 10 | F15: A1-01-ECC | G15: N3D PLA High Speed | H15: {=_xlfn.XLOOKUP($B15 & $D15 & $F15 & $G15, Produtos!$B:$B & Produtos!$C:$C & Produtos!$D:$D & Produtos!$E:$E, Produtos!$P:$P, "")} -> 1.1891693 | I15: =IFERROR($H15*I$5,"") -> 2.1405047 | J15: =IFERROR($E15*$I15,"") -> 21.405047 | L15: 65 | M15: =IFERROR(IF(OR($L15="",$L15=0),"",($L15-$J15)/$J15),"") -> 2.036667
A16: 46066 | B16: =IF($A16="","",PROPER(TEXT($A16,"mmm")) & "/" & TEXT($A16,"aa")) -> Fev/26 | C16: Marcelo Bach (Alpha) | D16: Projétil Munição 30x17mm | E16: 10 | F16: A1-01-ECC | G16: Masterprint PETG Basic | H16: {=_xlfn.XLOOKUP($B16 & $D16 & $F16 & $G16, Produtos!$B:$B & Produtos!$C:$C & Produtos!$D:$D & Produtos!$E:$E, Produtos!$P:$P, "")} -> 22.662777 | I16: =IFERROR($H16*I$5,"") -> 40.792999 | J16: =IFERROR($E16*$I16,"") -> 407.92999 | L16: 100 | M16: =IFERROR(IF(OR($L16="",$L16=0),"",($L16-$J16)/$J16),"") -> -0.7548599
A17: 46070 | B17: =IF($A17="","",PROPER(TEXT($A17,"mmm")) & "/" & TEXT($A17,"aa")) -> Fev/26 | C17: Fabio Olgins | D17: Escultura Olguins | E17: 1 | F17: A1-01-ECC | G17: N3D PLA High Speed | H17: {=_xlfn.XLOOKUP($B17 & $D17 & $F17 & $G17, Produtos!$B:$B & Produtos!$C:$C & Produtos!$D:$D & Produtos!$E:$E, Produtos!$P:$P, "")} -> 33.38078 | I17: =IFERROR($H17*I$5,"") -> 60.085404 | J17: =IFERROR($E17*$I17,"") -> 60.085404 | L17: 65 | M17: =IFERROR(IF(OR($L17="",$L17=0),"",($L17-$J17)/$J17),"") -> 0.081793507
A18: 46104 | B18: =IF($A18="","",PROPER(TEXT($A18,"mmm")) & "/" & TEXT($A18,"aa")) -> Mar/26 | C18: Marcelo Bach (Alpha) | D18: Cauda Moteiro 30x17mm | E18: 1 | F18: A1-01-ECC | G18: Masterprint PETG Basic | H18: {=_xlfn.XLOOKUP($B18 & $D18 & $F18 & $G18, Produtos!$B:$B & Produtos!$C:$C & Produtos!$D:$D & Produtos!$E:$E, Produtos!$P:$P, "")} -> 14.116119 | I18: =IFERROR($H18*I$5,"") -> 25.409015 | J18: =IFERROR($E18*$I18,"") -> 25.409015 | L18: 65 | M18: =IFERROR(IF(OR($L18="",$L18=0),"",($L18-$J18)/$J18),"") -> 1.5581472
A19: 46104 | B19: =IF($A19="","",PROPER(TEXT($A19,"mmm")) & "/" & TEXT($A19,"aa")) -> Mar/26 | C19: Marcelo Bach (Alpha) | D19: Porta Caneta Minecraft Dinamite | E19: 1 | F19: A1-01-ECC | G19: Bambu Lite PLA | H19: {=_xlfn.XLOOKUP($B19 & $D19 & $F19 & $G19, Produtos!$B:$B & Produtos!$C:$C & Produtos!$D:$D & Produtos!$E:$E, Produtos!$P:$P, "")} -> 39.47672 | I19: =IFERROR($H19*I$5,"") -> 71.058096 | J19: =IFERROR($E19*$I19,"") -> 71.058096 | L19: 100 | M19: =IFERROR(IF(OR($L19="",$L19=0),"",($L19-$J19)/$J19),"") -> 0.40729917
B20: =IF($A20="","",PROPER(TEXT($A20,"mmm")) & "/" & TEXT($A20,"aa")) | H20: {=_xlfn.XLOOKUP($B20 & $D20 & $F20 & $G20, Produtos!$B:$B & Produtos!$C:$C & Produtos!$D:$D & Produtos!$E:$E, Produtos!$P:$P, "")} -> 0 | I20: =IFERROR($H20*I$5,"") -> 0 | J20: =IFERROR($E20*$I20,"") -> 0 | M20: =IFERROR(IF(OR($L20="",$L20=0),"",($L20-$J20)/$J20),"")
B21: =IF($A21="","",PROPER(TEXT($A21,"mmm")) & "/" & TEXT($A21,"aa")) | H21: {=_xlfn.XLOOKUP($B21 & $D21 & $F21 & $G21, Produtos!$B:$B & Produtos!$C:$C & Produtos!$D:$D & Produtos!$E:$E, Produtos!$P:$P, "")} -> 0 | I21: =IFERROR($H21*I$5,"") -> 0 | J21: =IFERROR($E21*$I21,"") -> 0 | M21: =IFERROR(IF(OR($L21="",$L21=0),"",($L21-$J21)/$J21),"")
B22: =IF($A22="","",PROPER(TEXT($A22,"mmm")) & "/" & TEXT($A22,"aa")) | H22: {=_xlfn.XLOOKUP($B22 & $D22 & $F22 & $G22, Produtos!$B:$B & Produtos!$C:$C & Produtos!$D:$D & Produtos!$E:$E, Produtos!$P:$P, "")} -> 0 | I22: =IFERROR($H22*I$5,"") -> 0 | J22: =IFERROR($E22*$I22,"") -> 0 | M22: =IFERROR(IF(OR($L22="",$L22=0),"",($L22-$J22)/$J22),"")
B23: =IF($A23="","",PROPER(TEXT($A23,"mmm")) & "/" & TEXT($A23,"aa")) | H23: {=_xlfn.XLOOKUP($B23 & $D23 & $F23 & $G23, Produtos!$B:$B & Produtos!$C:$C & Produtos!$D:$D & Produtos!$E:$E, Produtos!$P:$P, "")} -> 0 | I23: =IFERROR($H23*I$5,"") -> 0 | J23: =IFERROR($E23*$I23,"") -> 0 | M23: =IFERROR(IF(OR($L23="",$L23=0),"",($L23-$J23)/$J23),"")
B24: =IF($A24="","",PROPER(TEXT($A24,"mmm")) & "/" & TEXT($A24,"aa")) | H24: {=_xlfn.XLOOKUP($B24 & $D24 & $F24 & $G24, Produtos!$B:$B & Produtos!$C:$C & Produtos!$D:$D & Produtos!$E:$E, Produtos!$P:$P, "")} -> 0 | I24: =IFERROR($H24*I$5,"") -> 0 | J24: =IFERROR($E24*$I24,"") -> 0 | M24: =IFERROR(IF(OR($L24="",$L24=0),"",($L24-$J24)/$J24),"")
B25: =IF($A25="","",PROPER(TEXT($A25,"mmm")) & "/" & TEXT($A25,"aa")) | H25: {=_xlfn.XLOOKUP($B25 & $D25 & $F25 & $G25, Produtos!$B:$B & Produtos!$C:$C & Produtos!$D:$D & Produtos!$E:$E, Produtos!$P:$P, "")} -> 0 | I25: =IFERROR($H25*I$5,"") -> 0 | J25: =IFERROR($E25*$I25,"") -> 0 | M25: =IFERROR(IF(OR($L25="",$L25=0),"",($L25-$J25)/$J25),"")
B26: =IF($A26="","",PROPER(TEXT($A26,"mmm")) & "/" & TEXT($A26,"aa")) | H26: {=_xlfn.XLOOKUP($B26 & $D26 & $F26 & $G26, Produtos!$B:$B & Produtos!$C:$C & Produtos!$D:$D & Produtos!$E:$E, Produtos!$P:$P, "")} -> 0 | I26: =IFERROR($H26*I$5,"") -> 0 | J26: =IFERROR($E26*$I26,"") -> 0 | M26: =IFERROR(IF(OR($L26="",$L26=0),"",($L26-$J26)/$J26),"")
B27: =IF($A27="","",PROPER(TEXT($A27,"mmm")) & "/" & TEXT($A27,"aa")) | H27: {=_xlfn.XLOOKUP($B27 & $D27 & $F27 & $G27, Produtos!$B:$B & Produtos!$C:$C & Produtos!$D:$D & Produtos!$E:$E, Produtos!$P:$P, "")} -> 0 | I27: =IFERROR($H27*I$5,"") -> 0 | J27: =IFERROR($E27*$I27,"") -> 0 | M27: =IFERROR(IF(OR($L27="",$L27=0),"",($L27-$J27)/$J27),"")
B28: =IF($A28="","",PROPER(TEXT($A28,"mmm")) & "/" & TEXT($A28,"aa")) | H28: {=_xlfn.XLOOKUP($B28 & $D28 & $F28 & $G28, Produtos!$B:$B & Produtos!$C:$C & Produtos!$D:$D & Produtos!$E:$E, Produtos!$P:$P, "")} -> 0 | I28: =IFERROR($H28*I$5,"") -> 0 | J28: =IFERROR($E28*$I28,"") -> 0 | M28: =IFERROR(IF(OR($L28="",$L28=0),"",($L28-$J28)/$J28),"")
B29: =IF($A29="","",PROPER(TEXT($A29,"mmm")) & "/" & TEXT($A29,"aa")) | H29: {=_xlfn.XLOOKUP($B29 & $D29 & $F29 & $G29, Produtos!$B:$B & Produtos!$C:$C & Produtos!$D:$D & Produtos!$E:$E, Produtos!$P:$P, "")} -> 0 | I29: =IFERROR($H29*I$5,"") -> 0 | J29: =IFERROR($E29*$I29,"") -> 0 | M29: =IFERROR(IF(OR($L29="",$L29=0),"",($L29-$J29)/$J29),"")
B30: =IF($A30="","",PROPER(TEXT($A30,"mmm")) & "/" & TEXT($A30,"aa")) | H30: {=_xlfn.XLOOKUP($B30 & $D30 & $F30 & $G30, Produtos!$B:$B & Produtos!$C:$C & Produtos!$D:$D & Produtos!$E:$E, Produtos!$P:$P, "")} -> 0 | I30: =IFERROR($H30*I$5,"") -> 0 | J30: =IFERROR($E30*$I30,"") -> 0 | M30: =IFERROR(IF(OR($L30="",$L30=0),"",($L30-$J30)/$J30),"")
B31: =IF($A31="","",PROPER(TEXT($A31,"mmm")) & "/" & TEXT($A31,"aa")) | H31: {=_xlfn.XLOOKUP($B31 & $D31 & $F31 & $G31, Produtos!$B:$B & Produtos!$C:$C & Produtos!$D:$D & Produtos!$E:$E, Produtos!$P:$P, "")} -> 0 | I31: =IFERROR($H31*I$5,"") -> 0 | J31: =IFERROR($E31*$I31,"") -> 0 | M31: =IFERROR(IF(OR($L31="",$L31=0),"",($L31-$J31)/$J31),"")
B32: =IF($A32="","",PROPER(TEXT($A32,"mmm")) & "/" & TEXT($A32,"aa")) | H32: {=_xlfn.XLOOKUP($B32 & $D32 & $F32 & $G32, Produtos!$B:$B & Produtos!$C:$C & Produtos!$D:$D & Produtos!$E:$E, Produtos!$P:$P, "")} -> 0 | I32: =IFERROR($H32*I$5,"") -> 0 | J32: =IFERROR($E32*$I32,"") -> 0 | M32: =IFERROR(IF(OR($L32="",$L32=0),"",($L32-$J32)/$J32),"")

Sheet Produtos
C2: Custos Gerais dos Produtos/Projetos
D5: Consumo | J5: Custos
A6: Data Cadastro | B6: Mês/Ano | C6: Produto | D6: Impressora | E6: Filamento | F6: Quantidade (g) | G6: Tempo (h) | H6: Trabalho (h) | I6: Insumos/Emb (R$) | J6: Filamento (R$) | K6: Eletricidade (R$) | L6: Depreciação (R$) | M6: Depreciação (%) | N6: Trabalho (R$) | O6: Taxa Falha (R$) | P6: Custo Unitário Total
A7: 46054 | B7: =IF($A7="","",PROPER(TEXT($A7,"mmm")) & "/" & TEXT($A7,"aa")) -> Fev/26 | C7: Porta Velas | D7: A1-01-ECC | E7: N3D PLA High Speed | F7: 174 | G7: 0.37152778 | H7: 0 | I7: 0 | J7: =IFERROR($F7/1000*VLOOKUP($E7,Filamentos!A$2:H$96,3,FALSE),"") -> 17.4 | K7: =IFERROR(G7*24*VLOOKUP(D7,Impressoras!A$2:G$100,6,FALSE)*Outros!$B$2,"") -> 1.605 | L7: =IFERROR(G7*24*VLOOKUP(D7,Impressoras!A$2:G$100,7,FALSE),"") -> 5.1500794 | M7: =IFERROR(L7*100/P7,"") -> 19.382633 | N7: =IFERROR(H7*24*Outros!$B$3,"") -> 0 | O7: =IFERROR(($I7+$J7+$K7+$L7+$N7)*Outros!$B$4,"") -> 2.4155079 | P7: =SUM(J7:L7)+SUM(N7:O7) -> 26.570587
A8: 46055 | B8: =IF($A8="","",PROPER(TEXT($A8,"mmm")) & "/" & TEXT($A8,"aa")) -> Fev/26 | C8: Miniatura Leonardo | D8: A1-01-ECC | E8: N3D PLA High Speed | F8: 193 | G8: 0.29166667 | H8: 0.0625 | I8: 35 | J8: =IFERROR($F8/1000*VLOOKUP($E8,Filamentos!A$2:H$96,3,FALSE),"") -> 19.3 | K8: =IFERROR(G8*24*VLOOKUP(D8,Impressoras!A$2:G$100,6,FALSE)*Outros!$B$2,"") -> 1.26 | L8: =IFERROR(G8*24*VLOOKUP(D8,Impressoras!A$2:G$100,7,FALSE),"") -> 4.043053 | M8: =IFERROR(L8*100/P8,"") -> 8.5906598 | N8: =IFERROR(H8*24*Outros!$B$3,"") -> 15 | O8: =IFERROR(($I8+$J8+$K8+$L8+$N8)*Outros!$B$4,"") -> 7.4603053 | P8: =SUM(J8:L8)+SUM(N8:O8) -> 47.063358
A9: 46056 | B9: =IF($A9="","",PROPER(TEXT($A9,"mmm")) & "/" & TEXT($A9,"aa")) -> Fev/26 | C9: Miniatura CAC Fabiano | D9: A1-01-ECC | E9: N3D PLA High Speed | F9: 107.73 | G9: 0.26736111 | H9: 0.0625 | I9: 0 | J9: =IFERROR($F9/1000*VLOOKUP($E9,Filamentos!A$2:H$96,3,FALSE),"") -> 10.773 | K9: =IFERROR(G9*24*VLOOKUP(D9,Impressoras!A$2:G$100,6,FALSE)*Outros!$B$2,"") -> 1.155 | L9: =IFERROR(G9*24*VLOOKUP(D9,Impressoras!A$2:G$100,7,FALSE),"") -> 3.7061319 | M9: =IFERROR(L9*100/P9,"") -> 10.998225 | N9: =IFERROR(H9*24*Outros!$B$3,"") -> 15 | O9: =IFERROR(($I9+$J9+$K9+$L9+$N9)*Outros!$B$4,"") -> 3.0634132 | P9: =SUM(J9:L9)+SUM(N9:O9) -> 33.697545
A10: 46057 | B10: =IF($A10="","",PROPER(TEXT($A10,"mmm")) & "/" & TEXT($A10,"aa")) -> Fev/26 | C10: Foguete NASA Educ. | D10: A1-01-ECC | E10: N3D PLA High Speed | F10: 84.28 | G10: 0.19305556 | H10: 0.020833333 | I10: 0 | J10: =IFERROR($F10/1000*VLOOKUP($E10,Filamentos!A$2:H$96,3,FALSE),"") -> 8.428 | K10: =IFERROR(G10*24*VLOOKUP(D10,Impressoras!A$2:G$100,6,FALSE)*Outros!$B$2,"") -> 0.834 | L10: =IFERROR(G10*24*VLOOKUP(D10,Impressoras!A$2:G$100,7,FALSE),"") -> 2.676116 | M10: =IFERROR(L10*100/P10,"") -> 14.363066 | N10: =IFERROR(H10*24*Outros!$B$3,"") -> 5 | O10: =IFERROR(($I10+$J10+$K10+$L10+$N10)*Outros!$B$4,"") -> 1.6938116 | P10: =SUM(J10:L10)+SUM(N10:O10) -> 18.631928
A11: 46058 | B11: =IF($A11="","",PROPER(TEXT($A11,"mmm")) & "/" & TEXT($A11,"aa")) -> Fev/26 | C11: Miniatura Tom Formatura | D11: A1-01-ECC | E11: Bambu Lite PLA | F11: =301.09+238.73+218.39+219.78 -> 977.99 | G11: 2.8583333 | H11: 0.020833333 | I11: 55 | J11: =IFERROR($F11/1000*VLOOKUP($E11,Filamentos!A$2:H$96,3,FALSE),"") -> 76.28322 | K11: =IFERROR(G11*24*VLOOKUP(D11,Impressoras!A$2:G$100,6,FALSE)*Outros!$B$2,"") -> 12.348 | L11: =IFERROR(G11*24*VLOOKUP(D11,Impressoras!A$2:G$100,7,FALSE),"") -> 39.621919 | M11: =IFERROR(L11*100/P11,"") -> 26.053605 | N11: =IFERROR(H11*24*Outros!$B$3,"") -> 5 | O11: =IFERROR(($I11+$J11+$K11+$L11+$N11)*Outros!$B$4,"") -> 18.825314 | P11: =SUM(J11:L11)+SUM(N11:O11) -> 152.07845
A12: 46059 | B12: =IF($A12="","",PROPER(TEXT($A12,"mmm")) & "/" & TEXT($A12,"aa")) -> Fev/26 | C12: Miniatura CAC Soares | D12: A1-01-ECC | E12: N3D PLA High Speed | F12: =(99.92+98.04) -> 197.96 | G12: 0.42291667 | H12: 0.0625 | I12: 5 | J12: =IFERROR($F12/1000*VLOOKUP($E12,Filamentos!A$2:H$96,3,FALSE),"") -> 19.796 | K12: =IFERROR(G12*24*VLOOKUP(D12,Impressoras!A$2:G$100,6,FALSE)*Outros!$B$2,"") -> 1.827 | L12: =IFERROR(G12*24*VLOOKUP(D12,Impressoras!A$2:G$100,7,FALSE),"") -> 5.8624268 | M12: =IFERROR(L12*100/P12,"") -> 12.411463 | N12: =IFERROR(H12*24*Outros!$B$3,"") -> 15 | O12: =IFERROR(($I12+$J12+$K12+$L12+$N12)*Outros!$B$4,"") -> 4.7485427 | P12: =SUM(J12:L12)+SUM(N12:O12) -> 47.23397
A13: 46060 | B13: =IF($A13="","",PROPER(TEXT($A13,"mmm")) & "/" & TEXT($A13,"aa")) -> Fev/26 | C13: Soldados Forças Especiais | D13: A1-01-ECC | E13: N3D PLA High Speed | F13: 131.39 | G13: 0.35694444 | H13: 0.020833333 | I13: 45 | J13: =IFERROR($F13/1000*VLOOKUP($E13,Filamentos!A$2:H$96,3,FALSE),"") -> 13.139 | K13: =IFERROR(G13*24*VLOOKUP(D13,Impressoras!A$2:G$100,6,FALSE)*Outros!$B$2,"") -> 1.542 | L13: =IFERROR(G13*24*VLOOKUP(D13,Impressoras!A$2:G$100,7,FALSE),"") -> 4.9479268 | M13: =IFERROR(L13*100/P13,"") -> 15.662051 | N13: =IFERROR(H13*24*Outros!$B$3,"") -> 5 | O13: =IFERROR(($I13+$J13+$K13+$L13+$N13)*Outros!$B$4,"") -> 6.9628927 | P13: =SUM(J13:L13)+SUM(N13:O13) -> 31.591819
A14: 46061 | B14: =IF($A14="","",PROPER(TEXT($A14,"mmm")) & "/" & TEXT($A14,"aa")) -> Fev/26 | C14: Escultura N. Sra. Div. Prev. | D14: A1-01-ECC | E14: Masterprint PETG Basic | F14: 100.99 | G14: 0.34097222 | H14: 0.020833333 | I14: 0 | J14: =IFERROR($F14/1000*VLOOKUP($E14,Filamentos!A$2:H$96,3,FALSE),"") -> 8.68514 | K14: =IFERROR(G14*24*VLOOKUP(D14,Impressoras!A$2:G$100,6,FALSE)*Outros!$B$2,"") -> 1.473 | L14: =IFERROR(G14*24*VLOOKUP(D14,Impressoras!A$2:G$100,7,FALSE),"") -> 4.7265215 | M14: =IFERROR(L14*100/P14,"") -> 21.608805 | N14: =IFERROR(H14*24*Outros!$B$3,"") -> 5 | O14: =IFERROR(($I14+$J14+$K14+$L14+$N14)*Outros!$B$4,"") -> 1.9884661 | P14: =SUM(J14:L14)+SUM(N14:O14) -> 21.873128
A15: 46062 | B15: =IF($A15="","",PROPER(TEXT($A15,"mmm")) & "/" & TEXT($A15,"aa")) -> Fev/26 | C15: Chav. Raquete 02 Cores | D15: A1-01-ECC | E15: N3D PLA High Speed | F15: 24.29 | G15: 0.090277778 | H15: 0.020833333 | I15: 0 | J15: =IFERROR($F15/1000*VLOOKUP($E15,Filamentos!A$2:H$96,3,FALSE),"") -> 2.429 | K15: =IFERROR(G15*24*VLOOKUP(D15,Impressoras!A$2:G$100,6,FALSE)*Outros!$B$2,"") -> 0.39 | L15: =IFERROR(G15*24*VLOOKUP(D15,Impressoras!A$2:G$100,7,FALSE),"") -> 1.2514212 | M15: =IFERROR(L15*100/P15,"") -> 12.542478 | N15: =IFERROR(H15*24*Outros!$B$3,"") -> 5 | O15: =IFERROR(($I15+$J15+$K15+$L15+$N15)*Outros!$B$4,"") -> 0.90704212 | P15: =SUM(J15:L15)+SUM(N15:O15) -> 9.9774633
A16: 46063 | B16: =IF($A16="","",PROPER(TEXT($A16,"mmm")) & "/" & TEXT($A16,"aa")) -> Fev/26 | C16: Vaso Mindfulness e Porta Vela | D16: A1-01-ECC | E16: Masterprint PETG Basic | F16: =(291.17+44.48) -> 335.65 | G16: 1.5104167 | H16: 0 | I16: 0 | J16: =IFERROR($F16/1000*VLOOKUP($E16,Filamentos!A$2:H$96,3,FALSE),"") -> 28.8659 | K16: =IFERROR(G16*24*VLOOKUP(D16,Impressoras!A$2:G$100,6,FALSE)*Outros!$B$2,"") -> 6.525 | L16: =IFERROR(G16*24*VLOOKUP(D16,Impressoras!A$2:G$100,7,FALSE),"") -> 20.937239 | M16: =IFERROR(L16*100/P16,"") -> 33.791021 | N16: =IFERROR(H16*24*Outros!$B$3,"") -> 0 | O16: =IFERROR(($I16+$J16+$K16+$L16+$N16)*Outros!$B$4,"") -> 5.6328139 | P16: =SUM(J16:L16)+SUM(N16:O16) -> 61.960953
A17: 46064 | B17: =IF($A17="","",PROPER(TEXT($A17,"mmm")) & "/" & TEXT($A17,"aa")) -> Fev/26 | C17: Chav. Glock 17 5cm | D17: A1-01-ECC | E17: N3D PLA High Speed | F17: =90.99/16 -> 5.686875 | G17: 0.022222222 | H17: 0.00034722222 | I17: 0.275 | J17: =IFERROR($F17/1000*VLOOKUP($E17,Filamentos!A$2:H$96,3,FALSE),"") -> 0.5686875 | K17: =IFERROR(G17*24*VLOOKUP(D17,Impressoras!A$2:G$100,6,FALSE)*Outros!$B$2,"") -> 0.096 | L17: =IFERROR(G17*24*VLOOKUP(D17,Impressoras!A$2:G$100,7,FALSE),"") -> 0.30804213 | M17: =IFERROR(L17*100/P17,"") -> 25.903977 | N17: =IFERROR(H17*24*Outros!$B$3,"") -> 0.083333333 | O17: =IFERROR(($I17+$J17+$K17+$L17+$N17)*Outros!$B$4,"") -> 0.1331063 | P17: =SUM(J17:L17)+SUM(N17:O17) -> 1.1891693
A18: 46065 | B18: =IF($A18="","",PROPER(TEXT($A18,"mmm")) & "/" & TEXT($A18,"aa")) -> Fev/26 | C18: Spectreman 20cm | D18: A1-01-ECC | E18: BambuPLA SILK | F18: 287.03 | G18: 0.69722222 | H18: 0.0625 | I18: 35 | J18: =IFERROR($F18/1000*VLOOKUP($E18,Filamentos!A$2:H$96,3,FALSE),"") -> 23.82349 | K18: =IFERROR(G18*24*VLOOKUP(D18,Impressoras!A$2:G$100,6,FALSE)*Outros!$B$2,"") -> 3.012 | L18: =IFERROR(G18*24*VLOOKUP(D18,Impressoras!A$2:G$100,7,FALSE),"") -> 9.6648219 | M18: =IFERROR(L18*100/P18,"") -> 16.067775 | N18: =IFERROR(H18*24*Outros!$B$3,"") -> 15 | O18: =IFERROR(($I18+$J18+$K18+$L18+$N18)*Outros!$B$4,"") -> 8.6500312 | P18: =SUM(J18:L18)+SUM(N18:O18) -> 60.150343
A19: 46066 | B19: =IF($A19="","",PROPER(TEXT($A19,"mmm")) & "/" & TEXT($A19,"aa")) -> Fev/26 | C19: Projétil Munição 30x17mm | D19: A1-01-ECC | E19: Masterprint PETG Basic | F19: 164.1 | G19: 0.33194444 | H19: 0 | I19: 5 | J19: =IFERROR($F19/1000*VLOOKUP($E19,Filamentos!A$2:H$96,3,FALSE),"") -> 14.1126 | K19: =IFERROR(G19*24*VLOOKUP(D19,Impressoras!A$2:G$100,6,FALSE)*Outros!$B$2,"") -> 1.434 | L19: =IFERROR(G19*24*VLOOKUP(D19,Impressoras!A$2:G$100,7,FALSE),"") -> 4.6013794 | M19: =IFERROR(L19*100/P19,"") -> 20.303687 | N19: =IFERROR(H19*24*Outros!$B$3,"") -> 0 | O19: =IFERROR(($I19+$J19+$K19+$L19+$N19)*Outros!$B$4,"") -> 2.5147979 | P19: =SUM(J19:L19)+SUM(N19:O19) -> 22.662777
A20: 46067 | B20: =IF($A20="","",PROPER(TEXT($A20,"mmm")) & "/" & TEXT($A20,"aa")) -> Fev/26 | C20: Chav. Casa 01 Cor 3cm | D20: A1-01-ECC | E20: N3D PLA High Speed | F20: 5 | G20: 0.0069444444 | H20: 0.0034722222 | I20: 0.28 | J20: =IFERROR($F20/1000*VLOOKUP($E20,Filamentos!A$2:H$96,3,FALSE),"") -> 0.5 | K20: =IFERROR(G20*24*VLOOKUP(D20,Impressoras!A$2:G$100,6,FALSE)*Outros!$B$2,"") -> 0.03 | L20: =IFERROR(G20*24*VLOOKUP(D20,Impressoras!A$2:G$100,7,FALSE),"") -> 0.096263167 | M20: =IFERROR(L20*100/P20,"") -> 5.8928594 | N20: =IFERROR(H20*24*Outros!$B$3,"") -> 0.83333333 | O20: =IFERROR(($I20+$J20+$K20+$L20+$N20)*Outros!$B$4,"") -> 0.17395965 | P20: =SUM(J20:L20)+SUM(N20:O20) -> 1.6335561
A21: 46068 | B21: =IF($A21="","",PROPER(TEXT($A21,"mmm")) & "/" & TEXT($A21,"aa")) -> Fev/26 | C21: Chav. Casa 02 Cores 3cm | D21: A1-01-ECC | E21: N3D PLA High Speed | F21: 5.75 | G21: 0.021087963 | H21: 0.00034722222 | I21: 0.28 | J21: =IFERROR($F21/1000*VLOOKUP($E21,Filamentos!A$2:H$96,3,FALSE),"") -> 0.575 | K21: =IFERROR(G21*24*VLOOKUP(D21,Impressoras!A$2:G$100,6,FALSE)*Outros!$B$2,"") -> 0.0911 | L21: =IFERROR(G21*24*VLOOKUP(D21,Impressoras!A$2:G$100,7,FALSE),"") -> 0.29231915 | M21: =IFERROR(L21*100/P21,"") -> 24.900949 | N21: =IFERROR(H21*24*Outros!$B$3,"") -> 0.083333333 | O21: =IFERROR(($I21+$J21+$K21+$L21+$N21)*Outros!$B$4,"") -> 0.13217525 | P21: =SUM(J21:L21)+SUM(N21:O21) -> 1.1739277
A22: 46069 | B22: =IF($A22="","",PROPER(TEXT($A22,"mmm")) & "/" & TEXT($A22,"aa")) -> Fev/26 | C22: Lum. Prisma Futurista Moderna | D22: A1-01-ECC | E22: Bambu Lite PLA | F22: 354.16 | G22: 0.47777778 | H22: 0.020833333 | I22: 26.5 | J22: =IFERROR($F22/1000*VLOOKUP($E22,Filamentos!A$2:H$96,3,FALSE),"") -> 27.62448 | K22: =IFERROR(G22*24*VLOOKUP(D22,Impressoras!A$2:G$100,6,FALSE)*Outros!$B$2,"") -> 2.064 | L22: =IFERROR(G22*24*VLOOKUP(D22,Impressoras!A$2:G$100,7,FALSE),"") -> 6.6229059 | M22: =IFERROR(L22*100/P22,"") -> 13.771175 | N22: =IFERROR(H22*24*Outros!$B$3,"") -> 5 | O22: =IFERROR(($I22+$J22+$K22+$L22+$N22)*Outros!$B$4,"") -> 6.7811386 | P22: =SUM(J22:L22)+SUM(N22:O22) -> 48.092524
A23: 46070 | B23: =IF($A23="","",PROPER(TEXT($A23,"mmm")) & "/" & TEXT($A23,"aa")) -> Fev/26 | C23: Escultura Olguins | D23: A1-01-ECC | E23: N3D PLA High Speed | F23: 177.83 | G23: 0.41597222 | H23: 0.020833333 | I23: 0 | J23: =IFERROR($F23/1000*VLOOKUP($E23,Filamentos!A$2:H$96,3,FALSE),"") -> 17.783 | K23: =IFERROR(G23*24*VLOOKUP(D23,Impressoras!A$2:G$100,6,FALSE)*Outros!$B$2,"") -> 1.797 | L23: =IFERROR(G23*24*VLOOKUP(D23,Impressoras!A$2:G$100,7,FALSE),"") -> 5.7661637 | M23: =IFERROR(L23*100/P23,"") -> 17.273903 | N23: =IFERROR(H23*24*Outros!$B$3,"") -> 5 | O23: =IFERROR(($I23+$J23+$K23+$L23+$N23)*Outros!$B$4,"") -> 3.0346164 | P23: =SUM(J23:L23)+SUM(N23:O23) -> 33.38078
A24: 46071 | B24: =IF($A24="","",PROPER(TEXT($A24,"mmm")) & "/" & TEXT($A24,"aa")) -> Fev/26 | C24: Vaso Espiral com Pés Peq. | D24: A1-01-ECC | E24: N3D PLA High Speed | F24: 73.9 | G24: 0.24305556 | H24: 0 | I24: 0 | J24: =IFERROR($F24/1000*VLOOKUP($E24,Filamentos!A$2:H$96,3,FALSE),"") -> 7.39 | K24: =IFERROR(G24*24*VLOOKUP(D24,Impressoras!A$2:G$100,6,FALSE)*Outros!$B$2,"") -> 1.05 | L24: =IFERROR(G24*24*VLOOKUP(D24,Impressoras!A$2:G$100,7,FALSE),"") -> 3.3692108 | M24: =IFERROR(L24*100/P24,"") -> 25.936695 | N24: =IFERROR(H24*24*Outros!$B$3,"") -> 0 | O24: =IFERROR(($I24+$J24+$K24+$L24+$N24)*Outros!$B$4,"") -> 1.1809211 | P24: =SUM(J24:L24)+SUM(N24:O24) -> 12.990132
A25: 46072 | B25: =IF($A25="","",PROPER(TEXT($A25,"mmm")) & "/" & TEXT($A25,"aa")) -> Fev/26 | C25: Porta Caneta Alpha 02 Cores | D25: A1-01-ECC | E25: N3D PLA High Speed | F25: 208.06 | G25: 0.49375 | H25: 0 | I25: 0 | J25: =IFERROR($F25/1000*VLOOKUP($E25,Filamentos!A$2:H$96,3,FALSE),"") -> 20.806 | K25: =IFERROR(G25*24*VLOOKUP(D25,Impressoras!A$2:G$100,6,FALSE)*Outros!$B$2,"") -> 2.133 | L25: =IFERROR(G25*24*VLOOKUP(D25,Impressoras!A$2:G$100,7,FALSE),"") -> 6.8443112 | M25: =IFERROR(L25*100/P25,"") -> 20.891233 | N25: =IFERROR(H25*24*Outros!$B$3,"") -> 0 | O25: =IFERROR(($I25+$J25+$K25+$L25+$N25)*Outros!$B$4,"") -> 2.9783311 | P25: =SUM(J25:L25)+SUM(N25:O25) -> 32.761642
A26: 46099 | B26: =IF($A26="","",PROPER(TEXT($A26,"mmm")) & "/" & TEXT($A26,"aa")) -> Mar/26 | C26: Cauda Moteiro 30x17mm | D26: A1-01-ECC | E26: Masterprint PETG Basic | F26: 20.02 | G26: 0.061111111 | H26: 0.041666667 | I26: 0 | J26: =IFERROR($F26/1000*VLOOKUP($E26,Filamentos!A$2:H$96,3,FALSE),"") -> 1.72172 | K26: =IFERROR(G26*24*VLOOKUP(D26,Impressoras!A$2:G$100,6,FALSE)*Outros!$B$2,"") -> 0.264 | L26: =IFERROR(G26*24*VLOOKUP(D26,Impressoras!A$2:G$100,7,FALSE),"") -> 0.84711587 | M26: =IFERROR(L26*100/P26,"") -> 6.0010534 | N26: =IFERROR(H26*24*Outros!$B$3,"") -> 10 | O26: =IFERROR(($I26+$J26+$K26+$L26+$N26)*Outros!$B$4,"") -> 1.2832836 | P26: =SUM(J26:L26)+SUM(N26:O26) -> 14.116119
A27: 46074 | B27: =IF($A27="","",PROPER(TEXT($A27,"mmm")) & "/" & TEXT($A27,"aa")) -> Fev/26 | C27: Chav. Casa 02 Cores 3cm | D27: A1-01-ECC | E27: N3D PLA High Speed | F27: 83.97 | G27: 0.25416667 | H27: 0.082638889 | I27: 13.78 | J27: =IFERROR($F27/1000*VLOOKUP($E27,Filamentos!A$2:H$96,3,FALSE),"") -> 8.397 | K27: =IFERROR(G27*24*VLOOKUP(D27,Impressoras!A$2:G$100,6,FALSE)*Outros!$B$2,"") -> 1.098 | L27: =IFERROR(G27*24*VLOOKUP(D27,Impressoras!A$2:G$100,7,FALSE),"") -> 3.5232319 | M27: =IFERROR(L27*100/P27,"") -> 9.3915981 | N27: =IFERROR(H27*24*Outros!$B$3,"") -> 19.833333 | O27: =IFERROR(($I27+$J27+$K27+$L27+$N27)*Outros!$B$4,"") -> 4.6631565 | P27: =SUM(J27:L27)+SUM(N27:O27) -> 37.514722
A28: 46103 | B28: =IF($A28="","",PROPER(TEXT($A28,"mmm")) & "/" & TEXT($A28,"aa")) -> Mar/26 | C28: Case TRT | D28: A1-01-ECC | E28: N3D PLA High Speed | F28: =141+87+9 -> 237 | G28: 0.26388889 | H28: 0.00069444444 | I28: 0 | J28: =IFERROR($F28/1000*VLOOKUP($E28,Filamentos!A$2:H$96,3,FALSE),"") -> 23.7 | K28: =IFERROR(G28*24*VLOOKUP(D28,Impressoras!A$2:G$100,6,FALSE)*Outros!$B$2,"") -> 1.14 | L28: =IFERROR(G28*24*VLOOKUP(D28,Impressoras!A$2:G$100,7,FALSE),"") -> 3.6580003 | M28: =IFERROR(L28*100/P28,"") -> 11.601233 | N28: =IFERROR(H28*24*Outros!$B$3,"") -> 0.16666667 | O28: =IFERROR(($I28+$J28+$K28+$L28+$N28)*Outros!$B$4,"") -> 2.8664667 | P28: =SUM(J28:L28)+SUM(N28:O28) -> 31.531134
A29: 46103 | B29: =IF($A29="","",PROPER(TEXT($A29,"mmm")) & "/" & TEXT($A29,"aa")) -> Mar/26 | C29: Case TRT 6 Frascos | D29: A1-01-ECC | E29: N3D PLA High Speed | F29: 209 | G29: 0.38055556 | H29: 0.00069444444 | I29: 0 | J29: =IFERROR($F29/1000*VLOOKUP($E29,Filamentos!A$2:H$96,3,FALSE),"") -> 20.9 | K29: =IFERROR(G29*24*VLOOKUP(D29,Impressoras!A$2:G$100,6,FALSE)*Outros!$B$2,"") -> 1.644 | L29: =IFERROR(G29*24*VLOOKUP(D29,Impressoras!A$2:G$100,7,FALSE),"") -> 5.2752215 | M29: =IFERROR(L29*100/P29,"") -> 17.135979 | N29: =IFERROR(H29*24*Outros!$B$3,"") -> 0.16666667 | O29: =IFERROR(($I29+$J29+$K29+$L29+$N29)*Outros!$B$4,"") -> 2.7985888 | P29: =SUM(J29:L29)+SUM(N29:O29) -> 30.784477
A30: 46103 | B30: =IF($A30="","",PROPER(TEXT($A30,"mmm")) & "/" & TEXT($A30,"aa")) -> Mar/26 | C30: Porta Caneta Minecraft Dinamite | D30: A1-01-ECC | E30: Bambu Lite PLA | F30: =52.12+19.53+197.6 -> 269.25 | G30: 0.81875 | H30: 0 | I30: 0 | J30: =IFERROR($F30/1000*VLOOKUP($E30,Filamentos!A$2:H$96,3,FALSE),"") -> 21.0015 | K30: =IFERROR(G30*24*VLOOKUP(D30,Impressoras!A$2:G$100,6,FALSE)*Outros!$B$2,"") -> 3.537 | L30: =IFERROR(G30*24*VLOOKUP(D30,Impressoras!A$2:G$100,7,FALSE),"") -> 11.349427 | M30: =IFERROR(L30*100/P30,"") -> 28.749672 | N30: =IFERROR(H30*24*Outros!$B$3,"") -> 0 | O30: =IFERROR(($I30+$J30+$K30+$L30+$N30)*Outros!$B$4,"") -> 3.5887927 | P30: =SUM(J30:L30)+SUM(N30:O30) -> 39.47672
A31: 46105 | B31: =IF($A31="","",PROPER(TEXT($A31,"mmm")) & "/" & TEXT($A31,"aa")) -> Mar/26 | C31: Enfeite Família | D31: A1-01-ECC | E31: Bambu Lite PLA | F31: 27.4 | G31: 0.060416667 | H31: 0.041666667 | I31: 0 | J31: =IFERROR($F31/1000*VLOOKUP($E31,Filamentos!A$2:H$96,3,FALSE),"") -> 2.1372 | K31: =IFERROR(G31*24*VLOOKUP(D31,Impressoras!A$2:G$100,6,FALSE)*Outros!$B$2,"") -> 0.261 | L31: =IFERROR(G31*24*VLOOKUP(D31,Impressoras!A$2:G$100,7,FALSE),"") -> 0.83748955 | M31: =IFERROR(L31*100/P31,"") -> 5.7522816 | N31: =IFERROR(H31*24*Outros!$B$3,"") -> 10 | O31: =IFERROR(($I31+$J31+$K31+$L31+$N31)*Outros!$B$4,"") -> 1.323569 | P31: =SUM(J31:L31)+SUM(N31:O31) -> 14.559259
A32: 46119 | B32: =IF($A32="","",PROPER(TEXT($A32,"mmm")) & "/" & TEXT($A32,"aa")) -> Abr/26 | C32: Caixa Munição 9mm | D32: A1-01-ECC | E32: Voolt3D PLA | F32: 256 | G32: 0.29791667 | H32: 0 | I32: 0 | J32: =IFERROR($F32/1000*VLOOKUP($E32,Filamentos!A$2:H$96,3,FALSE),"") -> 22.016 | K32: =IFERROR(G32*24*VLOOKUP(D32,Impressoras!A$2:G$100,6,FALSE)*Outros!$B$2,"") -> 1.287 | L32: =IFERROR(G32*24*VLOOKUP(D32,Impressoras!A$2:G$100,7,FALSE),"") -> 4.1296899 | M32: =IFERROR(L32*100/P32,"") -> 13.685364 | N32: =IFERROR(H32*24*Outros!$B$3,"") -> 0 | O32: =IFERROR(($I32+$J32+$K32+$L32+$N32)*Outros!$B$4,"") -> 2.743269 | P32: =SUM(J32:L32)+SUM(N32:O32) -> 30.175959
A33: 46119 | B33: =IF($A33="","",PROPER(TEXT($A33,"mmm")) & "/" & TEXT($A33,"aa")) -> Abr/26 | C33: Estojo de Clipe 223 556 300 10_15rd e Carregador Rápido | D33: A1-01-ECC | E33: Voolt3D PLA | F33: 527 | G33: 0.83819444 | H33: 0 | I33: 0 | J33: =IFERROR($F33/1000*VLOOKUP($E33,Filamentos!A$2:H$96,3,FALSE),"") -> 45.322 | K33: =IFERROR(G33*24*VLOOKUP(D33,Impressoras!A$2:G$100,6,FALSE)*Outros!$B$2,"") -> 3.621 | L33: =IFERROR(G33*24*VLOOKUP(D33,Impressoras!A$2:G$100,7,FALSE),"") -> 11.618964 | M33: =IFERROR(L33*100/P33,"") -> 17.441136 | N33: =IFERROR(H33*24*Outros!$B$3,"") -> 0 | O33: =IFERROR(($I33+$J33+$K33+$L33+$N33)*Outros!$B$4,"") -> 6.0561964 | P33: =SUM(J33:L33)+SUM(N33:O33) -> 66.618161
A34: 46124 | B34: =IF($A34="","",PROPER(TEXT($A34,"mmm")) & "/" & TEXT($A34,"aa")) -> Abr/26 | C34: BTS Prateleira de Exibição Temática | D34: A1-01-ECC | E34: Bambu Lite PLA | F34: 260 | G34: 0.30972222 | H34: 0 | I34: 0 | J34: =IFERROR($F34/1000*VLOOKUP($E34,Filamentos!A$2:H$96,3,FALSE),"") -> 20.28 | K34: =IFERROR(G34*24*VLOOKUP(D34,Impressoras!A$2:G$100,6,FALSE)*Outros!$B$2,"") -> 1.338 | L34: =IFERROR(G34*24*VLOOKUP(D34,Impressoras!A$2:G$100,7,FALSE),"") -> 4.2933372 | M34: =IFERROR(L34*100/P34,"") -> 15.063035 | N34: =IFERROR(H34*24*Outros!$B$3,"") -> 0 | O34: =IFERROR(($I34+$J34+$K34+$L34+$N34)*Outros!$B$4,"") -> 2.5911337 | P34: =SUM(J34:L34)+SUM(N34:O34) -> 28.502471
A35: 46125 | B35: =IF($A35="","",PROPER(TEXT($A35,"mmm")) & "/" & TEXT($A35,"aa")) -> Abr/26 | C35: Vaso Felicia Espiral 12cm | D35: A1-01-ECC | E35: Masterprint PETG Basic | F35: 61.94 | G35: 0.05625 | H35: 0 | I35: 0 | J35: =IFERROR($F35/1000*VLOOKUP($E35,Filamentos!A$2:H$96,3,FALSE),"") -> 5.32684 | K35: =IFERROR(G35*24*VLOOKUP(D35,Impressoras!A$2:G$100,6,FALSE)*Outros!$B$2,"") -> 0.243 | L35: =IFERROR(G35*24*VLOOKUP(D35,Impressoras!A$2:G$100,7,FALSE),"") -> 0.77973165 | M35: =IFERROR(L35*100/P35,"") -> 11.163697 | N35: =IFERROR(H35*24*Outros!$B$3,"") -> 0 | O35: =IFERROR(($I35+$J35+$K35+$L35+$N35)*Outros!$B$4,"") -> 0.63495716 | P35: =SUM(J35:L35)+SUM(N35:O35) -> 6.9845288
A36: 46125 | B36: =IF($A36="","",PROPER(TEXT($A36,"mmm")) & "/" & TEXT($A36,"aa")) -> Abr/26 | C36: Chaveiro Vinil BTS com Nome | D36: A1-01-ECC | E36: Bambu Lite PLA | F36: 19.62 | G36: 0.045833333 | H36: 0.020833333 | I36: 0.07 | J36: =IFERROR($F36/1000*VLOOKUP($E36,Filamentos!A$2:H$96,3,FALSE),"") -> 1.53036 | K36: =IFERROR(G36*24*VLOOKUP(D36,Impressoras!A$2:G$100,6,FALSE)*Outros!$B$2,"") -> 0.198 | L36: =IFERROR(G36*24*VLOOKUP(D36,Impressoras!A$2:G$100,7,FALSE),"") -> 0.6353369 | M36: =IFERROR(L36*100/P36,"") -> 7.8368284 | N36: =IFERROR(H36*24*Outros!$B$3,"") -> 5 | O36: =IFERROR(($I36+$J36+$K36+$L36+$N36)*Outros!$B$4,"") -> 0.74336969 | P36: =SUM(J36:L36)+SUM(N36:O36) -> 8.1070666
A37: 46125 | B37: =IF($A37="","",PROPER(TEXT($A37,"mmm")) & "/" & TEXT($A37,"aa")) -> Abr/26 | C37: Chaveiro Vinil BTS com Nome Mesa | D37: A1-01-ECC | E37: Bambu Lite PLA | F37: 206.11 | G37: 0.37777778 | H37: 0.020833333 | I37: =(0.07*13)+(0.07*60) -> 5.11 | J37: =IFERROR($F37/1000*VLOOKUP($E37,Filamentos!A$2:H$96,3,FALSE),"") -> 16.07658 | K37: =IFERROR(G37*24*VLOOKUP(D37,Impressoras!A$2:G$100,6,FALSE)*Outros!$B$2,"") -> 1.632 | L37: =IFERROR(G37*24*VLOOKUP(D37,Impressoras!A$2:G$100,7,FALSE),"") -> 5.2367163 | M37: =IFERROR(L37*100/P37,"") -> 16.757049 | N37: =IFERROR(H37*24*Outros!$B$3,"") -> 5 | O37: =IFERROR(($I37+$J37+$K37+$L37+$N37)*Outros!$B$4,"") -> 3.3055296 | P37: =SUM(J37:L37)+SUM(N37:O37) -> 31.250826
A38: 46125 | B38: =IF($A38="","",PROPER(TEXT($A38,"mmm")) & "/" & TEXT($A38,"aa")) -> Abr/26 | C38: Estante de Brincadeiras | D38: A1-01-ECC | E38: Masterprint PETG Basic | F38: 631.39 | G38: 0.66666667 | H38: 0 | I38: 0 | J38: =IFERROR($F38/1000*VLOOKUP($E38,Filamentos!A$2:H$96,3,FALSE),"") -> 54.29954 | K38: =IFERROR(G38*24*VLOOKUP(D38,Impressoras!A$2:G$100,6,FALSE)*Outros!$B$2,"") -> 2.88 | L38: =IFERROR(G38*24*VLOOKUP(D38,Impressoras!A$2:G$100,7,FALSE),"") -> 9.241264 | M38: =IFERROR(L38*100/P38,"") -> 12.64837 | N38: =IFERROR(H38*24*Outros!$B$3,"") -> 0 | O38: =IFERROR(($I38+$J38+$K38+$L38+$N38)*Outros!$B$4,"") -> 6.6420804 | P38: =SUM(J38:L38)+SUM(N38:O38) -> 73.062884
A39: 46127 | B39: =IF($A39="","",PROPER(TEXT($A39,"mmm")) & "/" & TEXT($A39,"aa")) -> Abr/26 | C39: Luminária Bulldog | D39: A1-01-ECC | E39: N3D PLA High Speed | F39: 368 | G39: 0.94444444 | H39: 0.020833333 | I39: =26.5+15 -> 41.5 | J39: =IFERROR($F39/1000*VLOOKUP($E39,Filamentos!A$2:H$96,3,FALSE),"") -> 36.8 | K39: =IFERROR(G39*24*VLOOKUP(D39,Impressoras!A$2:G$100,6,FALSE)*Outros!$B$2,"") -> 4.08 | L39: =IFERROR(G39*24*VLOOKUP(D39,Impressoras!A$2:G$100,7,FALSE),"") -> 13.091791 | M39: =IFERROR(L39*100/P39,"") -> 18.968395 | N39: =IFERROR(H39*24*Outros!$B$3,"") -> 5 | O39: =IFERROR(($I39+$J39+$K39+$L39+$N39)*Outros!$B$4,"") -> 10.047179 | P39: =SUM(J39:L39)+SUM(N39:O39) -> 69.01897
A40: 46127 | B40: =IF($A40="","",PROPER(TEXT($A40,"mmm")) & "/" & TEXT($A40,"aa")) -> Abr/26 | C40: BTS Fliptext Chaveiro - 10 Un | D40: A1-01-ECC | E40: N3D PLA High Speed | F40: =97+152 -> 249 | G40: 0.51736111 | H40: 0.0034722222 | I40: 0.7 | J40: =IFERROR($F40/1000*VLOOKUP($E40,Filamentos!A$2:H$96,3,FALSE),"") -> 24.9 | K40: =IFERROR(G40*24*VLOOKUP(D40,Impressoras!A$2:G$100,6,FALSE)*Outros!$B$2,"") -> 2.235 | L40: =IFERROR(G40*24*VLOOKUP(D40,Impressoras!A$2:G$100,7,FALSE),"") -> 7.1716059 | M40: =IFERROR(L40*100/P40,"") -> 18.519828 | N40: =IFERROR(H40*24*Outros!$B$3,"") -> 0.83333333 | O40: =IFERROR(($I40+$J40+$K40+$L40+$N40)*Outros!$B$4,"") -> 3.5839939 | P40: =SUM(J40:L40)+SUM(N40:O40) -> 38.723933
A41: 46127 | B41: =IF($A41="","",PROPER(TEXT($A41,"mmm")) & "/" & TEXT($A41,"aa")) -> Abr/26 | C41: BTS ARMY Fliptext - 4 un | D41: A1-01-ECC | E41: N3D PLA High Speed | F41: =147.8+83 -> 230.8 | G41: 0.40625 | H41: 0.0034722222 | I41: 0 | J41: =IFERROR($F41/1000*VLOOKUP($E41,Filamentos!A$2:H$96,3,FALSE),"") -> 23.08 | K41: =IFERROR(G41*24*VLOOKUP(D41,Impressoras!A$2:G$100,6,FALSE)*Outros!$B$2,"") -> 1.755 | L41: =IFERROR(G41*24*VLOOKUP(D41,Impressoras!A$2:G$100,7,FALSE),"") -> 5.6313952 | M41: =IFERROR(L41*100/P41,"") -> 16.356213 | N41: =IFERROR(H41*24*Outros!$B$3,"") -> 0.83333333 | O41: =IFERROR(($I41+$J41+$K41+$L41+$N41)*Outros!$B$4,"") -> 3.1299729 | P41: =SUM(J41:L41)+SUM(N41:O41) -> 34.429701
A42: 46128 | B42: =IF($A42="","",PROPER(TEXT($A42,"mmm")) & "/" & TEXT($A42,"aa")) -> Abr/26 | C42: Ovo Dragrão | D42: A1-01-ECC | E42: N3D PLA High Speed | F42: 71 | G42: 0.19444444 | H42: 0 | I42: 0 | J42: =IFERROR($F42/1000*VLOOKUP($E42,Filamentos!A$2:H$96,3,FALSE),"") -> 7.1 | K42: =IFERROR(G42*24*VLOOKUP(D42,Impressoras!A$2:G$100,6,FALSE)*Outros!$B$2,"") -> 0.84 | L42: =IFERROR(G42*24*VLOOKUP(D42,Impressoras!A$2:G$100,7,FALSE),"") -> 2.6953687 | M42: =IFERROR(L42*100/P42,"") -> 23.039494 | N42: =IFERROR(H42*24*Outros!$B$3,"") -> 0 | O42: =IFERROR(($I42+$J42+$K42+$L42+$N42)*Outros!$B$4,"") -> 1.0635369 | P42: =SUM(J42:L42)+SUM(N42:O42) -> 11.698906
A43: 46130 | B43: =IF($A43="","",PROPER(TEXT($A43,"mmm")) & "/" & TEXT($A43,"aa")) -> Abr/26 | C43: Suporte Celular Banco Carro | D43: A1-01-ECC | E43: N3D PLA High Speed | F43: 52 | G43: 0.041666667 | H43: 0 | I43: 0.07 | J43: =IFERROR($F43/1000*VLOOKUP($E43,Filamentos!A$2:H$96,3,FALSE),"") -> 5.2 | K43: =IFERROR(G43*24*VLOOKUP(D43,Impressoras!A$2:G$100,6,FALSE)*Outros!$B$2,"") -> 0.18 | L43: =IFERROR(G43*24*VLOOKUP(D43,Impressoras!A$2:G$100,7,FALSE),"") -> 0.577579 | M43: =IFERROR(L43*100/P43,"") -> 8.8041058 | N43: =IFERROR(H43*24*Outros!$B$3,"") -> 0 | O43: =IFERROR(($I43+$J43+$K43+$L43+$N43)*Outros!$B$4,"") -> 0.6027579 | P43: =SUM(J43:L43)+SUM(N43:O43) -> 6.5603369
A44: 46130 | B44: =IF($A44="","",PROPER(TEXT($A44,"mmm")) & "/" & TEXT($A44,"aa")) -> Abr/26 | C44: Suporte Celular Banco Carro 6 Un | D44: A1-01-ECC | E44: Masterprint PETG Basic | F44: 310 | G44: 0.5 | H44: 0.020833333 | I44: 0.36 | J44: =IFERROR($F44/1000*VLOOKUP($E44,Filamentos!A$2:H$96,3,FALSE),"") -> 26.66 | K44: =IFERROR(G44*24*VLOOKUP(D44,Impressoras!A$2:G$100,6,FALSE)*Outros!$B$2,"") -> 2.16 | L44: =IFERROR(G44*24*VLOOKUP(D44,Impressoras!A$2:G$100,7,FALSE),"") -> 6.930948 | M44: =IFERROR(L44*100/P44,"") -> 15.44947 | N44: =IFERROR(H44*24*Outros!$B$3,"") -> 5 | O44: =IFERROR(($I44+$J44+$K44+$L44+$N44)*Outros!$B$4,"") -> 4.1110948 | P44: =SUM(J44:L44)+SUM(N44:O44) -> 44.862043
A45: 46133 | B45: =IF($A45="","",PROPER(TEXT($A45,"mmm")) & "/" & TEXT($A45,"aa")) -> Abr/26 | C45: Chaveiro Munição 12 - 10 Un | D45: A1-01-ECC | E45: N3D PLA High Speed | F45: =81.77+27.86 -> 109.63 | G45: 0.17708333 | H45: 0.020833333 | I45: 0.7 | J45: =IFERROR($F45/1000*VLOOKUP($E45,Filamentos!A$2:H$96,3,FALSE),"") -> 10.963 | K45: =IFERROR(G45*24*VLOOKUP(D45,Impressoras!A$2:G$100,6,FALSE)*Outros!$B$2,"") -> 0.765 | L45: =IFERROR(G45*24*VLOOKUP(D45,Impressoras!A$2:G$100,7,FALSE),"") -> 2.4547107 | M45: =IFERROR(L45*100/P45,"") -> 11.594695 | N45: =IFERROR(H45*24*Outros!$B$3,"") -> 5 | O45: =IFERROR(($I45+$J45+$K45+$L45+$N45)*Outros!$B$4,"") -> 1.9882711 | P45: =SUM(J45:L45)+SUM(N45:O45) -> 21.170982
A46: 46133 | B46: =IF($A46="","",PROPER(TEXT($A46,"mmm")) & "/" & TEXT($A46,"aa")) -> Abr/26 | C46: Suporte Aro Headphone + Controle | D46: A1-01-ECC | E46: N3D PLA High Speed | F46: 335 | G46: 0.875 | H46: 0.020833333 | I46: 0 | J46: =IFERROR($F46/1000*VLOOKUP($E46,Filamentos!A$2:H$96,3,FALSE),"") -> 33.5 | K46: =IFERROR(G46*24*VLOOKUP(D46,Impressoras!A$2:G$100,6,FALSE)*Outros!$B$2,"") -> 3.78 | L46: =IFERROR(G46*24*VLOOKUP(D46,Impressoras!A$2:G$100,7,FALSE),"") -> 12.129159 | M46: =IFERROR(L46*100/P46,"") -> 20.265904 | N46: =IFERROR(H46*24*Outros!$B$3,"") -> 5 | O46: =IFERROR(($I46+$J46+$K46+$L46+$N46)*Outros!$B$4,"") -> 5.4409159 | P46: =SUM(J46:L46)+SUM(N46:O46) -> 59.850075
A47: 46133 | B47: =IF($A47="","",PROPER(TEXT($A47,"mmm")) & "/" & TEXT($A47,"aa")) -> Abr/26 | C47: Expositor com Display | D47: A1-01-ECC | E47: N3D PLA High Speed | F47: 94 | G47: 0.27083333 | H47: 0 | I47: 0 | J47: =IFERROR($F47/1000*VLOOKUP($E47,Filamentos!A$2:H$96,3,FALSE),"") -> 9.4 | K47: =IFERROR(G47*24*VLOOKUP(D47,Impressoras!A$2:G$100,6,FALSE)*Outros!$B$2,"") -> 1.17 | L47: =IFERROR(G47*24*VLOOKUP(D47,Impressoras!A$2:G$100,7,FALSE),"") -> 3.7542635 | M47: =IFERROR(L47*100/P47,"") -> 23.826473 | N47: =IFERROR(H47*24*Outros!$B$3,"") -> 0 | O47: =IFERROR(($I47+$J47+$K47+$L47+$N47)*Outros!$B$4,"") -> 1.4324264 | P47: =SUM(J47:L47)+SUM(N47:O47) -> 15.75669
A48: 46133 | B48: =IF($A48="","",PROPER(TEXT($A48,"mmm")) & "/" & TEXT($A48,"aa")) -> Abr/26 | C48: Chav. Capsula 12 - 5 Un | D48: A1-01-ECC | E48: N3D PLA High Speed | F48: 59 | G48: 0.10763889 | H48: 0.020833333 | I48: 0.35 | J48: =IFERROR($F48/1000*VLOOKUP($E48,Filamentos!A$2:H$96,3,FALSE),"") -> 5.9 | K48: =IFERROR(G48*24*VLOOKUP(D48,Impressoras!A$2:G$100,6,FALSE)*Outros!$B$2,"") -> 0.465 | L48: =IFERROR(G48*24*VLOOKUP(D48,Impressoras!A$2:G$100,7,FALSE),"") -> 1.4920791 | M48: =IFERROR(L48*100/P48,"") -> 10.524062 | N48: =IFERROR(H48*24*Outros!$B$3,"") -> 5 | O48: =IFERROR(($I48+$J48+$K48+$L48+$N48)*Outros!$B$4,"") -> 1.3207079 | P48: =SUM(J48:L48)+SUM(N48:O48) -> 14.177787
A49: 46133 | B49: =IF($A49="","",PROPER(TEXT($A49,"mmm")) & "/" & TEXT($A49,"aa")) -> Abr/26 | C49: Chav. Granada - 5 Un | D49: A1-01-ECC | E49: N3D PLA High Speed | F49: 73 | G49: 0.20833333 | H49: 0.020833333 | I49: 0.35 | J49: =IFERROR($F49/1000*VLOOKUP($E49,Filamentos!A$2:H$96,3,FALSE),"") -> 7.3 | K49: =IFERROR(G49*24*VLOOKUP(D49,Impressoras!A$2:G$100,6,FALSE)*Outros!$B$2,"") -> 0.9 | L49: =IFERROR(G49*24*VLOOKUP(D49,Impressoras!A$2:G$100,7,FALSE),"") -> 2.887895 | M49: =IFERROR(L49*100/P49,"") -> 16.286637 | N49: =IFERROR(H49*24*Outros!$B$3,"") -> 5 | O49: =IFERROR(($I49+$J49+$K49+$L49+$N49)*Outros!$B$4,"") -> 1.6437895 | P49: =SUM(J49:L49)+SUM(N49:O49) -> 17.731685
A50: 46133 | B50: =IF($A50="","",PROPER(TEXT($A50,"mmm")) & "/" & TEXT($A50,"aa")) -> Abr/26 | C50: Suporte AR com Carregador | D50: A1-01-ECC | E50: N3D PLA High Speed | F50: 94.72 | G50: 0.14305556 | H50: 0 | I50: 0.07 | J50: =IFERROR($F50/1000*VLOOKUP($E50,Filamentos!A$2:H$96,3,FALSE),"") -> 9.472 | K50: =IFERROR(G50*24*VLOOKUP(D50,Impressoras!A$2:G$100,6,FALSE)*Outros!$B$2,"") -> 0.618 | L50: =IFERROR(G50*24*VLOOKUP(D50,Impressoras!A$2:G$100,7,FALSE),"") -> 1.9830212 | M50: =IFERROR(L50*100/P50,"") -> 14.924159 | N50: =IFERROR(H50*24*Outros!$B$3,"") -> 0 | O50: =IFERROR(($I50+$J50+$K50+$L50+$N50)*Outros!$B$4,"") -> 1.2143021 | P50: =SUM(J50:L50)+SUM(N50:O50) -> 13.287323
A51: 46133 | B51: =IF($A51="","",PROPER(TEXT($A51,"mmm")) & "/" & TEXT($A51,"aa")) -> Abr/26 | C51: Bloco de Torno 9mm | D51: A1-01-ECC | E51: N3D PLA High Speed | F51: 82.16 | G51: 0.12847222 | H51: 0 | I51: 0 | J51: =IFERROR($F51/1000*VLOOKUP($E51,Filamentos!A$2:H$96,3,FALSE),"") -> 8.216 | K51: =IFERROR(G51*24*VLOOKUP(D51,Impressoras!A$2:G$100,6,FALSE)*Outros!$B$2,"") -> 0.555 | L51: =IFERROR(G51*24*VLOOKUP(D51,Impressoras!A$2:G$100,7,FALSE),"") -> 1.7808686 | M51: =IFERROR(L51*100/P51,"") -> 15.342983 | N51: =IFERROR(H51*24*Outros!$B$3,"") -> 0 | O51: =IFERROR(($I51+$J51+$K51+$L51+$N51)*Outros!$B$4,"") -> 1.0551869 | P51: =SUM(J51:L51)+SUM(N51:O51) -> 11.607055
A52: 46133 | B52: =IF($A52="","",PROPER(TEXT($A52,"mmm")) & "/" & TEXT($A52,"aa")) -> Abr/26 | C52: Bloco de Torno Fuzil | D52: A1-01-ECC | E52: N3D PLA High Speed | F52: 76.14 | G52: 0.11527778 | H52: 0 | I52: 0.07 | J52: =IFERROR($F52/1000*VLOOKUP($E52,Filamentos!A$2:H$96,3,FALSE),"") -> 7.614 | K52: =IFERROR(G52*24*VLOOKUP(D52,Impressoras!A$2:G$100,6,FALSE)*Outros!$B$2,"") -> 0.498 | L52: =IFERROR(G52*24*VLOOKUP(D52,Impressoras!A$2:G$100,7,FALSE),"") -> 1.5979686 | M52: =IFERROR(L52*100/P52,"") -> 14.951102 | N52: =IFERROR(H52*24*Outros!$B$3,"") -> 0 | O52: =IFERROR(($I52+$J52+$K52+$L52+$N52)*Outros!$B$4,"") -> 0.97799686 | P52: =SUM(J52:L52)+SUM(N52:O52) -> 10.687965
A53: 46133 | B53: =IF($A53="","",PROPER(TEXT($A53,"mmm")) & "/" & TEXT($A53,"aa")) -> Abr/26 | C53: Bumper GX4 | D53: A1-01-ECC | E53: N3D PLA High Speed | F53: 9.52 | G53: 0.020381944 | H53: 0 | I53: 0.07 | J53: =IFERROR($F53/1000*VLOOKUP($E53,Filamentos!A$2:H$96,3,FALSE),"") -> 0.952 | K53: =IFERROR(G53*24*VLOOKUP(D53,Impressoras!A$2:G$100,6,FALSE)*Outros!$B$2,"") -> 0.08805 | L53: =IFERROR(G53*24*VLOOKUP(D53,Impressoras!A$2:G$100,7,FALSE),"") -> 0.28253239 | M53: =IFERROR(L53*100/P53,"") -> 19.327168 | N53: =IFERROR(H53*24*Outros!$B$3,"") -> 0 | O53: =IFERROR(($I53+$J53+$K53+$L53+$N53)*Outros!$B$4,"") -> 0.13925824 | P53: =SUM(J53:L53)+SUM(N53:O53) -> 1.4618406
A54: 46133 | B54: =IF($A54="","",PROPER(TEXT($A54,"mmm")) & "/" & TEXT($A54,"aa")) -> Abr/26 | C54: Bumper G3 | D54: A1-01-ECC | E54: N3D PLA High Speed | F54: 7.42 | G54: 0.021446759 | H54: 0 | I54: 0.07 | J54: =IFERROR($F54/1000*VLOOKUP($E54,Filamentos!A$2:H$96,3,FALSE),"") -> 0.742 | K54: =IFERROR(G54*24*VLOOKUP(D54,Impressoras!A$2:G$100,6,FALSE)*Outros!$B$2,"") -> 0.09265 | L54: =IFERROR(G54*24*VLOOKUP(D54,Impressoras!A$2:G$100,7,FALSE),"") -> 0.29729275 | M54: =IFERROR(L54*100/P54,"") -> 23.742829 | N54: =IFERROR(H54*24*Outros!$B$3,"") -> 0 | O54: =IFERROR(($I54+$J54+$K54+$L54+$N54)*Outros!$B$4,"") -> 0.12019427 | P54: =SUM(J54:L54)+SUM(N54:O54) -> 1.252137
A55: 46133 | B55: =IF($A55="","",PROPER(TEXT($A55,"mmm")) & "/" & TEXT($A55,"aa")) -> Abr/26 | C55: Empunhadura AR-15 MLOK | D55: A1-01-ECC | E55: N3D PLA High Speed | F55: 19.56 | G55: 0.048611111 | H55: 0 | I55: 0.07 | J55: =IFERROR($F55/1000*VLOOKUP($E55,Filamentos!A$2:H$96,3,FALSE),"") -> 1.956 | K55: =IFERROR(G55*24*VLOOKUP(D55,Impressoras!A$2:G$100,6,FALSE)*Outros!$B$2,"") -> 0.21 | L55: =IFERROR(G55*24*VLOOKUP(D55,Impressoras!A$2:G$100,7,FALSE),"") -> 0.67384217 | M55: =IFERROR(L55*100/P55,"") -> 21.522821 | N55: =IFERROR(H55*24*Outros!$B$3,"") -> 0 | O55: =IFERROR(($I55+$J55+$K55+$L55+$N55)*Outros!$B$4,"") -> 0.29098422 | P55: =SUM(J55:L55)+SUM(N55:O55) -> 3.1308264
A56: 46134 | B56: =IF($A56="","",PROPER(TEXT($A56,"mmm")) & "/" & TEXT($A56,"aa")) -> Abr/26 | C56: Suporte Celular Mesa | D56: A1-01-ECC | E56: N3D PLA High Speed | F56: 18 | G56: 0.048611111 | H56: 0 | I56: 0.35 | J56: =IFERROR($F56/1000*VLOOKUP($E56,Filamentos!A$2:H$96,3,FALSE),"") -> 1.8 | K56: =IFERROR(G56*24*VLOOKUP(D56,Impressoras!A$2:G$100,6,FALSE)*Outros!$B$2,"") -> 0.21 | L56: =IFERROR(G56*24*VLOOKUP(D56,Impressoras!A$2:G$100,7,FALSE),"") -> 0.67384217 | M56: =IFERROR(L56*100/P56,"") -> 22.557452 | N56: =IFERROR(H56*24*Outros!$B$3,"") -> 0 | O56: =IFERROR(($I56+$J56+$K56+$L56+$N56)*Outros!$B$4,"") -> 0.30338422 | P56: =SUM(J56:L56)+SUM(N56:O56) -> 2.9872264
A57: 46135 | B57: =IF($A57="","",PROPER(TEXT($A57,"mmm")) & "/" & TEXT($A57,"aa")) -> Abr/26 | C57: Caixa de Jóias Coração | D57: A1-01-ECC | E57: N3D PLA High Speed | F57: 839.34 | G57: 1.09375 | H57: 0.020833333 | I57: 25 | J57: =IFERROR($F57/1000*VLOOKUP($E57,Filamentos!A$2:H$96,3,FALSE),"") -> 83.934 | K57: =IFERROR(G57*24*VLOOKUP(D57,Impressoras!A$2:G$100,6,FALSE)*Outros!$B$2,"") -> 4.725 | L57: =IFERROR(G57*24*VLOOKUP(D57,Impressoras!A$2:G$100,7,FALSE),"") -> 15.161449 | M57: =IFERROR(L57*100/P57,"") -> 12.406824 | N57: =IFERROR(H57*24*Outros!$B$3,"") -> 5 | O57: =IFERROR(($I57+$J57+$K57+$L57+$N57)*Outros!$B$4,"") -> 13.382045 | P57: =SUM(J57:L57)+SUM(N57:O57) -> 122.20249
A58: 46135 | B58: =IF($A58="","",PROPER(TEXT($A58,"mmm")) & "/" & TEXT($A58,"aa")) -> Abr/26 | C58: Kit Pote Coração | D58: A1-01-ECC | E58: N3D PLA High Speed | F58: 117.69 | G58: 0.21597222 | H58: 0 | I58: 25 | J58: =IFERROR($F58/1000*VLOOKUP($E58,Filamentos!A$2:H$96,3,FALSE),"") -> 11.769 | K58: =IFERROR(G58*24*VLOOKUP(D58,Impressoras!A$2:G$100,6,FALSE)*Outros!$B$2,"") -> 0.933 | L58: =IFERROR(G58*24*VLOOKUP(D58,Impressoras!A$2:G$100,7,FALSE),"") -> 2.9937845 | M58: =IFERROR(L58*100/P58,"") -> 15.14662 | N58: =IFERROR(H58*24*Outros!$B$3,"") -> 0 | O58: =IFERROR(($I58+$J58+$K58+$L58+$N58)*Outros!$B$4,"") -> 4.0695784 | P58: =SUM(J58:L58)+SUM(N58:O58) -> 19.765363

Sheet Estoque
A1: Tipo de Embalagem | B1: Valor | C1: Qtde. Comprada | D1: Valor Unitário | E1: Estoque Disponível | F1: Perda | N1: Tipo | O1: Valor | P1: Quantidade | Q1: Unitário | S1: Embalagem Grande | W1: Embalagem Pequena
A2: Argola Chaveiro | B2: 13.5 | C2: 50 | D2: =IFERROR(B2/C2,"") -> 0.27 | E2: 50 | N2: Almofada Colmeia | O2: 511 | P2: 600 | Q2: =O2/P2 -> 0.85166667 | S2: Material | T2: Quantidade | U2: Valor | W2: Material | X2: Quantidade | Y2: Valor
A3: Kit LED Bambu Lab | B3: 132.5 | C3: 5 | D3: =IFERROR(B3/C3,"") -> 26.5 | E3: 5 | N3: Caixa Grande | O3: 949.68 | P3: 300 | Q3: =O3/P3 -> 3.1656 | S3: Caixa Grande | T3: 1 | U3: =IFERROR(T3*VLOOKUP(S3,$N$2:$Q$12,4,FALSE),0) -> 3.1656 | W3: Caixa Pequena | X3: 1 | Y3: =IFERROR(X3*VLOOKUP(W3,$N$2:$Q$12,4,FALSE),0) -> 1.398
D4: =IFERROR(B4/C4,"") | E4: 0 | N4: Caixa Pequena | O4: 699 | P4: 500 | Q4: =O4/P4 -> 1.398 | S4: Almofada Colmeia | T4: 6 | U4: =IFERROR(T4*VLOOKUP(S4,$N$2:$Q$12,4,FALSE),0) -> 5.11 | W4: Almofada Colmeia | X4: 5 | Y4: =IFERROR(X4*VLOOKUP(W4,$N$2:$Q$12,4,FALSE),0) -> 4.2583333
D5: =IFERROR(B5/C5,"") | E5: 0 | N5: Fita gomada | O5: 29 | P5: 150 | Q5: =O5/P5 -> 0.19333333 | S5: Fita gomada | T5: 1 | U5: =IFERROR(T5*VLOOKUP(S5,$N$2:$Q$12,4,FALSE),0) -> 0.19333333 | W5: Fita gomada | X5: 1 | Y5: =IFERROR(X5*VLOOKUP(W5,$N$2:$Q$12,4,FALSE),0) -> 0.19333333
D6: =IFERROR(B6/C6,"") | E6: 0 | N6: Etiqueta | O6: 20 | P6: 150 | Q6: =O6/P6 -> 0.13333333 | S6: Etiqueta | T6: 1 | U6: =IFERROR(T6*VLOOKUP(S6,$N$2:$Q$12,4,FALSE),0) -> 0.13333333 | W6: Etiqueta | X6: 1 | Y6: =IFERROR(X6*VLOOKUP(W6,$N$2:$Q$12,4,FALSE),0) -> 0.13333333
D7: =IFERROR(B7/C7,"") | E7: 0 | N7: Caixa Fone | O7: 0.96 | Q7: 0.96 | S7: Argola Chaveiro | T7: 1 | U7: =IFERROR(T7*VLOOKUP(S7,$N$2:$Q$12,4,FALSE),0) -> 0.27 | Y7: =IFERROR(X7*VLOOKUP(W7,$N$2:$Q$12,4,FALSE),0) -> 0
D8: =IFERROR(B8/C8,"") | E8: 0 | N8: Argola Chaveiro | O8: 13.5 | P8: 50 | Q8: =O8/P8 -> 0.27 | S8: Total | U8: 8.6 | W8: Total | Y8: 5.98
D9: =IFERROR(B9/C9,"") | E9: 0 | N9: Kit LED Bambu Lab | O9: 132.5 | P9: 5 | Q9: =O9/P9 -> 26.5
D10: =IFERROR(B10/C10,"") | E10: 0 | Q10: =O10/P10 -> #DIV/0!
D11: =IFERROR(B11/C11,"") | E11: 0 | Q11: =O11/P11 -> #DIV/0!
D12: =IFERROR(B12/C12,"") | E12: 0 | Q12: =O12/P12 -> #DIV/0!
D13: =IFERROR(B13/C13,"") | E13: 0
D14: =IFERROR(B14/C14,"") | E14: 0
D15: =IFERROR(B15/C15,"") | E15: 0
D16: =IFERROR(B16/C16,"") | E16: 0
D17: =IFERROR(B17/C17,"") | E17: 0
D18: =IFERROR(B18/C18,"") | E18: 0
D19: =IFERROR(B19/C19,"") | E19: 0
D20: =IFERROR(B20/C20,"") | E20: 0
D21: =IFERROR(B21/C21,"") | E21: 0
D22: =IFERROR(B22/C22,"") | E22: 0
D23: =IFERROR(B23/C23,"") | E23: 0
D24: =IFERROR(B24/C24,"") | E24: 0 | S24: Grande | T24: 8.6
D25: =IFERROR(B25/C25,"") | E25: 0 | S25: Pequena | T25: 4.93
D26: =IFERROR(B26/C26,"") | E26: 0
D27: =IFERROR(B27/C27,"") | E27: 0
D28: =IFERROR(B28/C28,"") | E28: 0
D29: =IFERROR(B29/C29,"") | E29: 0
D30: =IFERROR(B30/C30,"") | E30: 0
D31: =IFERROR(B31/C31,"") | E31: 0

Sheet Impressoras
A1: Impressora | B1: Fabricante | C1: Preço [R$] | D1: Depreciação (h) | E1: Custo Manut (R$) | F1: Cons Máx Energia (kW/h) | G1: Depreciação [R$/h]
A2: A1-01-ECC | B2: Bambu Lab | C2: 4775.79 | D2: 10000 | E2: 1000 | F2: 0.15 | G2: =(C2+E2)/D2 -> 0.577579
A3: H2D | B3: Bambu Lab | C3: 22000 | D3: 25000 | E3: 3000 | F3: 0.3 | G3: =(C3+E3)/D3 -> 1

Sheet Outros
B1: 46054 | D1: Expurgo (%) | E1: Taxa Marketplace
A2: Custo de Energia | B2: 1.2 | D2: 0 | E2: Shoppe
A3: Custo de Trabalho | B3: 10 | C3: =B5&"/h" -> R$/h | D3: 0.05 | E3: Mercado livre
A4: Taxa de falha | B4: 0.1 | C4: % | D4: 0.1 | E4: Amazon
A5: Unidade monetária | B5: R$ | D5: 0.15 | E5: Aliexpress
A6: Taxa marketplace | B6: 0.2 | D6: 0.2 | E6: Facebook
A7: Imposto | B7: 0 | D7: 0.25 | E7: Instagram
A8: Taxa fixa | B8: 4 | D8: 0.3
D9: 0.35
I29: 0.12291667
I30: 0.054166667
I31: =SUM(I29:I30) -> 0.17708333

Sheet Filamentos
A1: Fabricante Filamento | B1: Diâmetro (mm) | C1: Preço Carretel (R$) | D1: Peso Carretel (g) | E1: Densidade (g/cm³) | F1: Temp. do bico (°C) | G1: Temp. da Mesa (°C) | H1: Comprimento p/ rolo (m)
A2: Voolt3D PLA | B2: 1.75 | C2: 86 | D2: 1000 | E2: 1.24 | F2: 220 | G2: 60 | H2: =D2/E2*4/(PI()*(B2/100)^2)/10 -> 335283.62
A3: BambuPLA SILK | B3: 1.75 | C3: 83 | D3: 1000 | E3: 1.24 | F3: 260 | G3: 80 | H3: =D3/E3*4/(PI()*(B3/100)^2)/10 -> 335283.62
A4: Bambu Lite PLA | B4: 1.75 | C4: 78 | D4: 1000 | E4: 1.24 | F4: 220 | G4: 115 | H4: =D4/E4*4/(PI()*(B4/100)^2)/10 -> 335283.62
A5: N3D PLA High Speed | B5: 1.75 | C5: 100 | D5: 1000 | E5: 1.24 | F5: 220 | G5: 100 | H5: =D5/E5*4/(PI()*(B5/100)^2)/10 -> 335283.62
A6: Masterprint PETG Basic | B6: 1.75 | C6: 86 | D6: 1000 | E6: 1.24 | F6: 220 | G6: 100 | H6: =D6/E6*4/(PI()*(B6/100)^2)/10 -> 335283.62

Sheet DRE
C1: DRE - Demonstrativo de Resultados do Exercício
A5: Mês / Ano | B5: Filamento (kg) | C5: Tempo Impressão | D5: Tempo Trabalho | E5: Insumos | F5: Embalagens | G5: Custo Total | H5: Energia Elétrica | I5: Vendas | J5: % Lucro ou Prejuízo | K5: Depreciação (R$) | L5: H2D | M5: Horas A1 Combo | N5: Horas H2D | O5: % Vida Consumida A1 | P5: % Vida Restante A1 | Q5: % Vida Consumida H2D | R5: % Vida Restante H2D
A6: =IF(DATE(YEAR(MIN(Vendas!$A:$A)),MONTH(MIN(Vendas!$A:$A))+ROW()-ROW($A$6),1)>DATE(YEAR(MAX(Vendas!$A:$A)),MONTH(MAX(Vendas!$A:$A)),1),"",DATE(YEAR(MIN(Vendas!$A:$A)),MONTH(MIN(Vendas!$A:$A))+ROW()-ROW($A$6),1)) -> 46054 | B6: =SUMIFS(Vendas!#REF!,Vendas!$A:$A,">="&A6,Vendas!$A:$A,"<"&EOMONTH(A6,0)+1)/1000 -> #REF! | C6: =SUMIFS(Vendas!#REF!,Vendas!$A:$A,">="&A6,Vendas!$A:$A,"<"&EOMONTH(A6,0)+1) -> #REF! | D6: =SUMIFS(Vendas!#REF!,Vendas!$A:$A,">="&A6,Vendas!$A:$A,"<"&EOMONTH(A6,0)+1) -> #REF! | E6: =SUMIFS(Vendas!#REF!,Vendas!$A:$A,">="&A6,Vendas!$A:$A,"<"&EOMONTH(A6,0)+1) -> #REF! | F6: =SUMIFS(Vendas!#REF!,Vendas!$A:$A,">="&A6,Vendas!$A:$A,"<"&EOMONTH(A6,0)+1) -> #REF! | G6: =SUMIFS(Vendas!$G:$G,Vendas!$A:$A,">="&A6,Vendas!$A:$A,"<"&EOMONTH(A6,0)+1) -> 0 | H6: =SUMIFS(Vendas!#REF!,Vendas!$A:$A,">="&A6,Vendas!$A:$A,"<"&EOMONTH(A6,0)+1) -> #REF! | I6: =SUMIFS(Vendas!$K:$K,Vendas!$A:$A,">="&A6,Vendas!$A:$A,"<"&EOMONTH(A6,0)+1) -> 80 | J6: =IF(G6=0,"",(I6-G6)/I6) | K6: =SUMIFS(Vendas!#REF!,Vendas!$A:$A,">="&A6,Vendas!$A:$A,"<"&EOMONTH(A6,0)+1) -> #REF! | L6: 0 | M6: 193.91667 | N6: 0 | O6: 0.019391667 | P6: 0.98060833 | Q6: 0 | R6: 1
A7: =IF(DATE(YEAR(MIN(Vendas!$A:$A)),MONTH(MIN(Vendas!$A:$A))+ROW()-ROW($A$6),1)>DATE(YEAR(MAX(Vendas!$A:$A)),MONTH(MAX(Vendas!$A:$A)),1),"",DATE(YEAR(MIN(Vendas!$A:$A)),MONTH(MIN(Vendas!$A:$A))+ROW()-ROW($A$6),1)) -> 46082 | B7: =SUMIFS(Vendas!#REF!,Vendas!$A:$A,">="&A7,Vendas!$A:$A,"<"&EOMONTH(A7,0)+1)/1000 -> #REF! | C7: =SUMIFS(Vendas!#REF!,Vendas!$A:$A,">="&A7,Vendas!$A:$A,"<"&EOMONTH(A7,0)+1) -> #REF! | D7: =SUMIFS(Vendas!#REF!,Vendas!$A:$A,">="&A7,Vendas!$A:$A,"<"&EOMONTH(A7,0)+1) -> #REF! | E7: =SUMIFS(Vendas!#REF!,Vendas!$A:$A,">="&A7,Vendas!$A:$A,"<"&EOMONTH(A7,0)+1) -> #REF! | F7: =SUMIFS(Vendas!#REF!,Vendas!$A:$A,">="&A7,Vendas!$A:$A,"<"&EOMONTH(A7,0)+1) -> #REF! | G7: =SUMIFS(Vendas!$G:$G,Vendas!$A:$A,">="&A7,Vendas!$A:$A,"<"&EOMONTH(A7,0)+1) -> 0 | H7: =SUMIFS(Vendas!#REF!,Vendas!$A:$A,">="&A7,Vendas!$A:$A,"<"&EOMONTH(A7,0)+1) -> #REF! | I7: =SUMIFS(Vendas!$K:$K,Vendas!$A:$A,">="&A7,Vendas!$A:$A,"<"&EOMONTH(A7,0)+1) -> 0 | J7: =IF(G7=0,"",(I7-G7)/I7) | K7: =SUMIFS(Vendas!#REF!,Vendas!$A:$A,">="&A7,Vendas!$A:$A,"<"&EOMONTH(A7,0)+1) -> #REF! | L7: 0 | M7: 0 | N7: 0 | O7: 0 | P7: 1 | Q7: 0 | R7: 1
A8: =IF(DATE(YEAR(MIN(Vendas!$A:$A)),MONTH(MIN(Vendas!$A:$A))+ROW()-ROW($A$6),1)>DATE(YEAR(MAX(Vendas!$A:$A)),MONTH(MAX(Vendas!$A:$A)),1),"",DATE(YEAR(MIN(Vendas!$A:$A)),MONTH(MIN(Vendas!$A:$A))+ROW()-ROW($A$6),1)) | B8: =SUMIFS(Vendas!#REF!,Vendas!$A:$A,">="&A8,Vendas!$A:$A,"<"&EOMONTH(A8,0)+1)/1000 -> #REF! | C8: =SUMIFS(Vendas!#REF!,Vendas!$A:$A,">="&A8,Vendas!$A:$A,"<"&EOMONTH(A8,0)+1) -> #REF! | D8: =SUMIFS(Vendas!#REF!,Vendas!$A:$A,">="&A8,Vendas!$A:$A,"<"&EOMONTH(A8,0)+1) -> #REF! | E8: =SUMIFS(Vendas!#REF!,Vendas!$A:$A,">="&A8,Vendas!$A:$A,"<"&EOMONTH(A8,0)+1) -> #REF! | F8: =SUMIFS(Vendas!#REF!,Vendas!$A:$A,">="&A8,Vendas!$A:$A,"<"&EOMONTH(A8,0)+1) -> #REF! | G8: =SUMIFS(Vendas!$G:$G,Vendas!$A:$A,">="&A8,Vendas!$A:$A,"<"&EOMONTH(A8,0)+1) -> 0 | H8: =SUMIFS(Vendas!#REF!,Vendas!$A:$A,">="&A8,Vendas!$A:$A,"<"&EOMONTH(A8,0)+1) -> #REF! | I8: =SUMIFS(Vendas!$K:$K,Vendas!$A:$A,">="&A8,Vendas!$A:$A,"<"&EOMONTH(A8,0)+1) -> 0 | J8: =IF(G8=0,"",(I8-G8)/I8) | K8: =SUMIFS(Vendas!#REF!,Vendas!$A:$A,">="&A8,Vendas!$A:$A,"<"&EOMONTH(A8,0)+1) -> #REF! | L8: 0 | M8: 0 | N8: 0 | O8: 0 | P8: 1 | Q8: 0 | R8: 1
A9: =IF(DATE(YEAR(MIN(Vendas!$A:$A)),MONTH(MIN(Vendas!$A:$A))+ROW()-ROW($A$6),1)>DATE(YEAR(MAX(Vendas!$A:$A)),MONTH(MAX(Vendas!$A:$A)),1),"",DATE(YEAR(MIN(Vendas!$A:$A)),MONTH(MIN(Vendas!$A:$A))+ROW()-ROW($A$6),1)) | B9: =SUMIFS(Vendas!#REF!,Vendas!$A:$A,">="&A9,Vendas!$A:$A,"<"&EOMONTH(A9,0)+1)/1000 -> #REF! | C9: =SUMIFS(Vendas!#REF!,Vendas!$A:$A,">="&A9,Vendas!$A:$A,"<"&EOMONTH(A9,0)+1) -> #REF! | D9: =SUMIFS(Vendas!#REF!,Vendas!$A:$A,">="&A9,Vendas!$A:$A,"<"&EOMONTH(A9,0)+1) -> #REF! | E9: =SUMIFS(Vendas!#REF!,Vendas!$A:$A,">="&A9,Vendas!$A:$A,"<"&EOMONTH(A9,0)+1) -> #REF! | F9: =SUMIFS(Vendas!#REF!,Vendas!$A:$A,">="&A9,Vendas!$A:$A,"<"&EOMONTH(A9,0)+1) -> #REF! | G9: =SUMIFS(Vendas!$G:$G,Vendas!$A:$A,">="&A9,Vendas!$A:$A,"<"&EOMONTH(A9,0)+1) -> 0 | H9: =SUMIFS(Vendas!#REF!,Vendas!$A:$A,">="&A9,Vendas!$A:$A,"<"&EOMONTH(A9,0)+1) -> #REF! | I9: =SUMIFS(Vendas!$K:$K,Vendas!$A:$A,">="&A9,Vendas!$A:$A,"<"&EOMONTH(A9,0)+1) -> 0 | J9: =IF(G9=0,"",(I9-G9)/I9) | K9: =SUMIFS(Vendas!#REF!,Vendas!$A:$A,">="&A9,Vendas!$A:$A,"<"&EOMONTH(A9,0)+1) -> #REF! | L9: 0 | M9: 0 | N9: 0 | O9: 0 | P9: 1 | Q9: 0 | R9: 1
A10: =IF(DATE(YEAR(MIN(Vendas!$A:$A)),MONTH(MIN(Vendas!$A:$A))+ROW()-ROW($A$6),1)>DATE(YEAR(MAX(Vendas!$A:$A)),MONTH(MAX(Vendas!$A:$A)),1),"",DATE(YEAR(MIN(Vendas!$A:$A)),MONTH(MIN(Vendas!$A:$A))+ROW()-ROW($A$6),1)) | B10: =SUMIFS(Vendas!#REF!,Vendas!$A:$A,">="&A10,Vendas!$A:$A,"<"&EOMONTH(A10,0)+1)/1000 -> #REF! | C10: =SUMIFS(Vendas!#REF!,Vendas!$A:$A,">="&A10,Vendas!$A:$A,"<"&EOMONTH(A10,0)+1) -> #REF! | D10: =SUMIFS(Vendas!#REF!,Vendas!$A:$A,">="&A10,Vendas!$A:$A,"<"&EOMONTH(A10,0)+1) -> #REF! | E10: =SUMIFS(Vendas!#REF!,Vendas!$A:$A,">="&A10,Vendas!$A:$A,"<"&EOMONTH(A10,0)+1) -> #REF! | F10: =SUMIFS(Vendas!#REF!,Vendas!$A:$A,">="&A10,Vendas!$A:$A,"<"&EOMONTH(A10,0)+1) -> #REF! | G10: =SUMIFS(Vendas!$G:$G,Vendas!$A:$A,">="&A10,Vendas!$A:$A,"<"&EOMONTH(A10,0)+1) -> 0 | H10: =SUMIFS(Vendas!#REF!,Vendas!$A:$A,">="&A10,Vendas!$A:$A,"<"&EOMONTH(A10,0)+1) -> #REF! | I10: =SUMIFS(Vendas!$K:$K,Vendas!$A:$A,">="&A10,Vendas!$A:$A,"<"&EOMONTH(A10,0)+1) -> 0 | J10: =IF(G10=0,"",(I10-G10)/I10) | K10: =SUMIFS(Vendas!#REF!,Vendas!$A:$A,">="&A10,Vendas!$A:$A,"<"&EOMONTH(A10,0)+1) -> #REF! | L10: 0 | M10: 0 | N10: 0 | O10: 0 | P10: 1 | Q10: 0 | R10: 1
A11: =IF(DATE(YEAR(MIN(Vendas!$A:$A)),MONTH(MIN(Vendas!$A:$A))+ROW()-ROW($A$6),1)>DATE(YEAR(MAX(Vendas!$A:$A)),MONTH(MAX(Vendas!$A:$A)),1),"",DATE(YEAR(MIN(Vendas!$A:$A)),MONTH(MIN(Vendas!$A:$A))+ROW()-ROW($A$6),1)) | B11: =SUMIFS(Vendas!#REF!,Vendas!$A:$A,">="&A11,Vendas!$A:$A,"<"&EOMONTH(A11,0)+1)/1000 -> #REF! | C11: =SUMIFS(Vendas!#REF!,Vendas!$A:$A,">="&A11,Vendas!$A:$A,"<"&EOMONTH(A11,0)+1) -> #REF! | D11: =SUMIFS(Vendas!#REF!,Vendas!$A:$A,">="&A11,Vendas!$A:$A,"<"&EOMONTH(A11,0)+1) -> #REF! | E11: =SUMIFS(Vendas!#REF!,Vendas!$A:$A,">="&A11,Vendas!$A:$A,"<"&EOMONTH(A11,0)+1) -> #REF! | F11: =SUMIFS(Vendas!#REF!,Vendas!$A:$A,">="&A11,Vendas!$A:$A,"<"&EOMONTH(A11,0)+1) -> #REF! | G11: =SUMIFS(Vendas!$G:$G,Vendas!$A:$A,">="&A11,Vendas!$A:$A,"<"&EOMONTH(A11,0)+1) -> 0 | H11: =SUMIFS(Vendas!#REF!,Vendas!$A:$A,">="&A11,Vendas!$A:$A,"<"&EOMONTH(A11,0)+1) -> #REF! | I11: =SUMIFS(Vendas!$K:$K,Vendas!$A:$A,">="&A11,Vendas!$A:$A,"<"&EOMONTH(A11,0)+1) -> 0 | J11: =IF(G11=0,"",(I11-G11)/I11) | K11: =SUMIFS(Vendas!#REF!,Vendas!$A:$A,">="&A11,Vendas!$A:$A,"<"&EOMONTH(A11,0)+1) -> #REF! | L11: 0 | M11: 0 | N11: 0 | O11: 0 | P11: 1 | Q11: 0 | R11: 1
A12: =IF(DATE(YEAR(MIN(Vendas!$A:$A)),MONTH(MIN(Vendas!$A:$A))+ROW()-ROW($A$6),1)>DATE(YEAR(MAX(Vendas!$A:$A)),MONTH(MAX(Vendas!$A:$A)),1),"",DATE(YEAR(MIN(Vendas!$A:$A)),MONTH(MIN(Vendas!$A:$A))+ROW()-ROW($A$6),1)) | B12: =SUMIFS(Vendas!#REF!,Vendas!$A:$A,">="&A12,Vendas!$A:$A,"<"&EOMONTH(A12,0)+1)/1000 -> #REF! | C12: =SUMIFS(Vendas!#REF!,Vendas!$A:$A,">="&A12,Vendas!$A:$A,"<"&EOMONTH(A12,0)+1) -> #REF! | D12: =SUMIFS(Vendas!#REF!,Vendas!$A:$A,">="&A12,Vendas!$A:$A,"<"&EOMONTH(A12,0)+1) -> #REF! | E12: =SUMIFS(Vendas!#REF!,Vendas!$A:$A,">="&A12,Vendas!$A:$A,"<"&EOMONTH(A12,0)+1) -> #REF! | F12: =SUMIFS(Vendas!#REF!,Vendas!$A:$A,">="&A12,Vendas!$A:$A,"<"&EOMONTH(A12,0)+1) -> #REF! | G12: =SUMIFS(Vendas!$G:$G,Vendas!$A:$A,">="&A12,Vendas!$A:$A,"<"&EOMONTH(A12,0)+1) -> 0 | H12: =SUMIFS(Vendas!#REF!,Vendas!$A:$A,">="&A12,Vendas!$A:$A,"<"&EOMONTH(A12,0)+1) -> #REF! | I12: =SUMIFS(Vendas!$K:$K,Vendas!$A:$A,">="&A12,Vendas!$A:$A,"<"&EOMONTH(A12,0)+1) -> 0 | J12: =IF(G12=0,"",(I12-G12)/I12) | K12: =SUMIFS(Vendas!#REF!,Vendas!$A:$A,">="&A12,Vendas!$A:$A,"<"&EOMONTH(A12,0)+1) -> #REF! | L12: 0 | M12: 0 | N12: 0 | O12: 0 | P12: 1 | Q12: 0 | R12: 1
A13: =IF(DATE(YEAR(MIN(Vendas!$A:$A)),MONTH(MIN(Vendas!$A:$A))+ROW()-ROW($A$6),1)>DATE(YEAR(MAX(Vendas!$A:$A)),MONTH(MAX(Vendas!$A:$A)),1),"",DATE(YEAR(MIN(Vendas!$A:$A)),MONTH(MIN(Vendas!$A:$A))+ROW()-ROW($A$6),1)) | B13: =SUMIFS(Vendas!#REF!,Vendas!$A:$A,">="&A13,Vendas!$A:$A,"<"&EOMONTH(A13,0)+1)/1000 -> #REF! | C13: =SUMIFS(Vendas!#REF!,Vendas!$A:$A,">="&A13,Vendas!$A:$A,"<"&EOMONTH(A13,0)+1) -> #REF! | D13: =SUMIFS(Vendas!#REF!,Vendas!$A:$A,">="&A13,Vendas!$A:$A,"<"&EOMONTH(A13,0)+1) -> #REF! | E13: =SUMIFS(Vendas!#REF!,Vendas!$A:$A,">="&A13,Vendas!$A:$A,"<"&EOMONTH(A13,0)+1) -> #REF! | F13: =SUMIFS(Vendas!#REF!,Vendas!$A:$A,">="&A13,Vendas!$A:$A,"<"&EOMONTH(A13,0)+1) -> #REF! | G13: =SUMIFS(Vendas!$G:$G,Vendas!$A:$A,">="&A13,Vendas!$A:$A,"<"&EOMONTH(A13,0)+1) -> 0 | H13: =SUMIFS(Vendas!#REF!,Vendas!$A:$A,">="&A13,Vendas!$A:$A,"<"&EOMONTH(A13,0)+1) -> #REF! | I13: =SUMIFS(Vendas!$K:$K,Vendas!$A:$A,">="&A13,Vendas!$A:$A,"<"&EOMONTH(A13,0)+1) -> 0 | J13: =IF(G13=0,"",(I13-G13)/I13) | K13: =SUMIFS(Vendas!#REF!,Vendas!$A:$A,">="&A13,Vendas!$A:$A,"<"&EOMONTH(A13,0)+1) -> #REF! | L13: 0 | M13: 0 | N13: 0 | O13: 0 | P13: 1 | Q13: 0 | R13: 1
A14: =IF(DATE(YEAR(MIN(Vendas!$A:$A)),MONTH(MIN(Vendas!$A:$A))+ROW()-ROW($A$6),1)>DATE(YEAR(MAX(Vendas!$A:$A)),MONTH(MAX(Vendas!$A:$A)),1),"",DATE(YEAR(MIN(Vendas!$A:$A)),MONTH(MIN(Vendas!$A:$A))+ROW()-ROW($A$6),1)) | B14: =SUMIFS(Vendas!#REF!,Vendas!$A:$A,">="&A14,Vendas!$A:$A,"<"&EOMONTH(A14,0)+1)/1000 -> #REF! | C14: =SUMIFS(Vendas!#REF!,Vendas!$A:$A,">="&A14,Vendas!$A:$A,"<"&EOMONTH(A14,0)+1) -> #REF! | D14: =SUMIFS(Vendas!#REF!,Vendas!$A:$A,">="&A14,Vendas!$A:$A,"<"&EOMONTH(A14,0)+1) -> #REF! | E14: =SUMIFS(Vendas!#REF!,Vendas!$A:$A,">="&A14,Vendas!$A:$A,"<"&EOMONTH(A14,0)+1) -> #REF! | F14: =SUMIFS(Vendas!#REF!,Vendas!$A:$A,">="&A14,Vendas!$A:$A,"<"&EOMONTH(A14,0)+1) -> #REF! | G14: =SUMIFS(Vendas!$G:$G,Vendas!$A:$A,">="&A14,Vendas!$A:$A,"<"&EOMONTH(A14,0)+1) -> 0 | H14: =SUMIFS(Vendas!#REF!,Vendas!$A:$A,">="&A14,Vendas!$A:$A,"<"&EOMONTH(A14,0)+1) -> #REF! | I14: =SUMIFS(Vendas!$K:$K,Vendas!$A:$A,">="&A14,Vendas!$A:$A,"<"&EOMONTH(A14,0)+1) -> 0 | J14: =IF(G14=0,"",(I14-G14)/I14) | K14: =SUMIFS(Vendas!#REF!,Vendas!$A:$A,">="&A14,Vendas!$A:$A,"<"&EOMONTH(A14,0)+1) -> #REF! | L14: 0 | M14: 0 | N14: 0 | O14: 0 | P14: 1 | Q14: 0 | R14: 1
A15: =IF(DATE(YEAR(MIN(Vendas!$A:$A)),MONTH(MIN(Vendas!$A:$A))+ROW()-ROW($A$6),1)>DATE(YEAR(MAX(Vendas!$A:$A)),MONTH(MAX(Vendas!$A:$A)),1),"",DATE(YEAR(MIN(Vendas!$A:$A)),MONTH(MIN(Vendas!$A:$A))+ROW()-ROW($A$6),1)) | B15: =SUMIFS(Vendas!#REF!,Vendas!$A:$A,">="&A15,Vendas!$A:$A,"<"&EOMONTH(A15,0)+1)/1000 -> #REF! | C15: =SUMIFS(Vendas!#REF!,Vendas!$A:$A,">="&A15,Vendas!$A:$A,"<"&EOMONTH(A15,0)+1) -> #REF! | D15: =SUMIFS(Vendas!#REF!,Vendas!$A:$A,">="&A15,Vendas!$A:$A,"<"&EOMONTH(A15,0)+1) -> #REF! | E15: =SUMIFS(Vendas!#REF!,Vendas!$A:$A,">="&A15,Vendas!$A:$A,"<"&EOMONTH(A15,0)+1) -> #REF! | F15: =SUMIFS(Vendas!#REF!,Vendas!$A:$A,">="&A15,Vendas!$A:$A,"<"&EOMONTH(A15,0)+1) -> #REF! | G15: =SUMIFS(Vendas!$G:$G,Vendas!$A:$A,">="&A15,Vendas!$A:$A,"<"&EOMONTH(A15,0)+1) -> 0 | H15: =SUMIFS(Vendas!#REF!,Vendas!$A:$A,">="&A15,Vendas!$A:$A,"<"&EOMONTH(A15,0)+1) -> #REF! | I15: =SUMIFS(Vendas!$K:$K,Vendas!$A:$A,">="&A15,Vendas!$A:$A,"<"&EOMONTH(A15,0)+1) -> 0 | J15: =IF(G15=0,"",(I15-G15)/I15) | K15: =SUMIFS(Vendas!#REF!,Vendas!$A:$A,">="&A15,Vendas!$A:$A,"<"&EOMONTH(A15,0)+1) -> #REF! | L15: 0 | M15: 0 | N15: 0 | O15: 0 | P15: 1 | Q15: 0 | R15: 1
A16: =IF(DATE(YEAR(MIN(Vendas!$A:$A)),MONTH(MIN(Vendas!$A:$A))+ROW()-ROW($A$6),1)>DATE(YEAR(MAX(Vendas!$A:$A)),MONTH(MAX(Vendas!$A:$A)),1),"",DATE(YEAR(MIN(Vendas!$A:$A)),MONTH(MIN(Vendas!$A:$A))+ROW()-ROW($A$6),1)) | B16: =SUMIFS(Vendas!#REF!,Vendas!$A:$A,">="&A16,Vendas!$A:$A,"<"&EOMONTH(A16,0)+1)/1000 -> #REF! | C16: =SUMIFS(Vendas!#REF!,Vendas!$A:$A,">="&A16,Vendas!$A:$A,"<"&EOMONTH(A16,0)+1) -> #REF! | D16: =SUMIFS(Vendas!#REF!,Vendas!$A:$A,">="&A16,Vendas!$A:$A,"<"&EOMONTH(A16,0)+1) -> #REF! | E16: =SUMIFS(Vendas!#REF!,Vendas!$A:$A,">="&A16,Vendas!$A:$A,"<"&EOMONTH(A16,0)+1) -> #REF! | F16: =SUMIFS(Vendas!#REF!,Vendas!$A:$A,">="&A16,Vendas!$A:$A,"<"&EOMONTH(A16,0)+1) -> #REF! | G16: =SUMIFS(Vendas!$G:$G,Vendas!$A:$A,">="&A16,Vendas!$A:$A,"<"&EOMONTH(A16,0)+1) -> 0 | H16: =SUMIFS(Vendas!#REF!,Vendas!$A:$A,">="&A16,Vendas!$A:$A,"<"&EOMONTH(A16,0)+1) -> #REF! | I16: =SUMIFS(Vendas!$K:$K,Vendas!$A:$A,">="&A16,Vendas!$A:$A,"<"&EOMONTH(A16,0)+1) -> 0 | J16: =IF(G16=0,"",(I16-G16)/I16) | K16: =SUMIFS(Vendas!#REF!,Vendas!$A:$A,">="&A16,Vendas!$A:$A,"<"&EOMONTH(A16,0)+1) -> #REF! | L16: 0 | M16: 0 | N16: 0 | O16: 0 | P16: 1 | Q16: 0 | R16: 1
A17: =IF(DATE(YEAR(MIN(Vendas!$A:$A)),MONTH(MIN(Vendas!$A:$A))+ROW()-ROW($A$6),1)>DATE(YEAR(MAX(Vendas!$A:$A)),MONTH(MAX(Vendas!$A:$A)),1),"",DATE(YEAR(MIN(Vendas!$A:$A)),MONTH(MIN(Vendas!$A:$A))+ROW()-ROW($A$6),1)) | B17: =SUMIFS(Vendas!#REF!,Vendas!$A:$A,">="&A17,Vendas!$A:$A,"<"&EOMONTH(A17,0)+1)/1000 -> #REF! | C17: =SUMIFS(Vendas!#REF!,Vendas!$A:$A,">="&A17,Vendas!$A:$A,"<"&EOMONTH(A17,0)+1) -> #REF! | D17: =SUMIFS(Vendas!#REF!,Vendas!$A:$A,">="&A17,Vendas!$A:$A,"<"&EOMONTH(A17,0)+1) -> #REF! | E17: =SUMIFS(Vendas!#REF!,Vendas!$A:$A,">="&A17,Vendas!$A:$A,"<"&EOMONTH(A17,0)+1) -> #REF! | F17: =SUMIFS(Vendas!#REF!,Vendas!$A:$A,">="&A17,Vendas!$A:$A,"<"&EOMONTH(A17,0)+1) -> #REF! | G17: =SUMIFS(Vendas!$G:$G,Vendas!$A:$A,">="&A17,Vendas!$A:$A,"<"&EOMONTH(A17,0)+1) -> 0 | H17: =SUMIFS(Vendas!#REF!,Vendas!$A:$A,">="&A17,Vendas!$A:$A,"<"&EOMONTH(A17,0)+1) -> #REF! | I17: =SUMIFS(Vendas!$K:$K,Vendas!$A:$A,">="&A17,Vendas!$A:$A,"<"&EOMONTH(A17,0)+1) -> 0 | J17: =IF(G17=0,"",(I17-G17)/I17) | K17: =SUMIFS(Vendas!#REF!,Vendas!$A:$A,">="&A17,Vendas!$A:$A,"<"&EOMONTH(A17,0)+1) -> #REF! | L17: 0 | M17: 0 | N17: 0 | O17: 0 | P17: 1 | Q17: 0 | R17: 1
A18: =IF(DATE(YEAR(MIN(Vendas!$A:$A)),MONTH(MIN(Vendas!$A:$A))+ROW()-ROW($A$6),1)>DATE(YEAR(MAX(Vendas!$A:$A)),MONTH(MAX(Vendas!$A:$A)),1),"",DATE(YEAR(MIN(Vendas!$A:$A)),MONTH(MIN(Vendas!$A:$A))+ROW()-ROW($A$6),1)) | B18: =SUMIFS(Vendas!#REF!,Vendas!$A:$A,">="&A18,Vendas!$A:$A,"<"&EOMONTH(A18,0)+1)/1000 -> #REF! | C18: =SUMIFS(Vendas!#REF!,Vendas!$A:$A,">="&A18,Vendas!$A:$A,"<"&EOMONTH(A18,0)+1) -> #REF! | D18: =SUMIFS(Vendas!#REF!,Vendas!$A:$A,">="&A18,Vendas!$A:$A,"<"&EOMONTH(A18,0)+1) -> #REF! | E18: =SUMIFS(Vendas!#REF!,Vendas!$A:$A,">="&A18,Vendas!$A:$A,"<"&EOMONTH(A18,0)+1) -> #REF! | F18: =SUMIFS(Vendas!#REF!,Vendas!$A:$A,">="&A18,Vendas!$A:$A,"<"&EOMONTH(A18,0)+1) -> #REF! | G18: =SUMIFS(Vendas!$G:$G,Vendas!$A:$A,">="&A18,Vendas!$A:$A,"<"&EOMONTH(A18,0)+1) -> 0 | H18: =SUMIFS(Vendas!#REF!,Vendas!$A:$A,">="&A18,Vendas!$A:$A,"<"&EOMONTH(A18,0)+1) -> #REF! | I18: =SUMIFS(Vendas!$K:$K,Vendas!$A:$A,">="&A18,Vendas!$A:$A,"<"&EOMONTH(A18,0)+1) -> 0 | J18: =IF(G18=0,"",(I18-G18)/I18) | K18: =SUMIFS(Vendas!#REF!,Vendas!$A:$A,">="&A18,Vendas!$A:$A,"<"&EOMONTH(A18,0)+1) -> #REF! | L18: 0 | M18: 0 | N18: 0 | O18: 0 | P18: 1 | Q18: 0 | R18: 1
A19: SubTotal | B19: =SUM(B$2:INDEX(B:B,MATCH(9.99999999999999E+307,A:A))) -> #REF! | C19: =SUM(C$2:INDEX(C:C,MATCH(9.99999999999999E+307,A:A))) -> #REF! | D19: =SUM(D$6:INDEX(D:D,MATCH(9.99999999999999E+307,A:A))) -> #REF! | E19: =SUM(E$6:INDEX(E:E,MATCH(9.99999999999999E+307,A:A))) -> #REF! | F19: =SUM(F$6:INDEX(F:F,MATCH(9.99999999999999E+307,A:A))) -> #REF! | G19: =SUM(G$2:INDEX(G:G,MATCH(9.99999999999999E+307,A:A))) -> 0 | H19: =SUM(H$6:INDEX(H:H,MATCH(9.99999999999999E+307,A:A))) -> #REF! | I19: =SUM(I$2:INDEX(I:I,MATCH(9.99999999999999E+307,A:A))) -> 80 | J19: =IF(G19=0,"",(I19-G19)/G19) | K19: =SUM(K$2:INDEX(K:K,MATCH(9.99999999999999E+307,A:A))) -> #REF! | L19: =SUM(L$6:INDEX(N:N,MATCH(9.99999999999999E+307,A:A))) -> 193.91667 | M19: =SUM(M$6:INDEX(M:M,MATCH(9.99999999999999E+307,A:A))) -> 193.91667 | N19: =SUM(N$6:INDEX(N:N,MATCH(9.99999999999999E+307,A:A))) -> 0 | O19: 0.019391667 | P19: 0.98060833 | Q19: 0 | R19: 1
J21: Colocar um % de reserva ou planejamento de compra ou investimentos em novos equipamentos? | O21: Quando uma impressora se pagará?
